[
  {
    "obj": {
      "type": 1,
      "start_x": 2.490598923241495,
      "start_y": 2.3905989232414955,
      "start_z": 2.490598923241495,
      "scale_x": 0.288,
      "scale_y": 0.432,
      "scale_z": 0.288,
      "mode": "0"
    }
  },
 
  {
    "obj": {
      "type": 3,
      "start_x": 0.1811978464829906,
      "start_y": -0.20820215351700944,
      "start_z": 0.1811978464829906,
      "scale_x": 0.12800000000000003,
      "scale_y": 0.5894,
      "scale_z": 0.12800000000000003,
      "mode": "0"
    }
  }
]