[
  {
    "obj": {
      "type": 1,
      "start_x": 3.6452994616207475,
      "start_y": 3.8252994616207476,
      "start_z": 3.6452994616207475,
      "scale_x": 0.2,
      "scale_y": 0.02,
      "scale_z": 0.2,
      "mode": "1"
    }
  },
  {
    "obj": {
      "type": 3,
      "start_x": 3.6452994616207475,
      "start_y": 4.182799461620748,
      "start_z": 3.6452994616207475,
      "scale_x": 0.02,
      "scale_y": 0.3375,
      "scale_z": 0.02,
      "mode": "1"
    }
  },
  {
    "obj": {
      "type": 1,
      "start_x": 3.6452994616207475,
      "start_y": 4.540299461620748,
      "start_z": 3.6452994616207475,
      "scale_x": 0.2,
      "scale_y": 0.02,
      "scale_z": 0.2,
      "mode": "1"
    }
  },
  {
    "obj": {
      "type": 5,
      "start_x": 4.157399461620748,
      "start_y": 4.540299461620748,
      "start_z": 3.6452994616207475,
      "scale_x": 0.3121,
      "scale_y": 0.02,
      "scale_z": 0.02,
      "mode": "1"
    }
  },
  {
    "obj": {
      "type": 1,
      "start_x": 4.669499461620748,
      "start_y": 4.540299461620748,
      "start_z": 3.6452994616207475,
      "scale_x": 0.2,
      "scale_y": 0.02,
      "scale_z": 0.2,
      "mode": "1"
    }
  },
  {
    "obj": {
      "type": 3,
      "start_x": 3.2479491924311215,
      "start_y": 3.0733491924311216,
      "start_z": 3.2479491924311215,
      "scale_x": 0.02,
      "scale_y": 0.1946,
      "scale_z": 0.02,
      "mode": "1"
    }
  },
  {
    "obj": {
      "type": 1,
      "start_x": 3.2479491924311215,
      "start_y": 3.2879491924311215,
      "start_z": 3.2479491924311215,
      "scale_x": 0.2,
      "scale_y": 0.02,
      "scale_z": 0.2,
      "mode": "1"
    }
  },
  {
    "obj": {
      "type": 4,
      "start_x": 2.7668491924311214,
      "start_y": 3.2879491924311215,
      "start_z": 3.2479491924311215,
      "scale_x": 0.2811,
      "scale_y": 0.02,
      "scale_z": 0.02,
      "mode": "1"
    }
  },
  {
    "obj": {
      "type": 1,
      "start_x": 2.2857491924311213,
      "start_y": 3.2879491924311215,
      "start_z": 3.2479491924311215,
      "scale_x": 0.2,
      "scale_y": 0.02,
      "scale_z": 0.2,
      "mode": "1"
    }
  },
  {
    "obj": {
      "type": 6,
      "start_x": 2.2857491924311213,
      "start_y": 3.2879491924311215,
      "start_z": 2.8446491924311212,
      "scale_x": 0.02,
      "scale_y": 0.02,
      "scale_z": 0.2033,
      "mode": "1"
    }
  },
  {
    "obj": {
      "type": 1,
      "start_x": 2.2857491924311213,
      "start_y": 3.2879491924311215,
      "start_z": 2.441349192431121,
      "scale_x": 0.2,
      "scale_y": 0.02,
      "scale_z": 0.2,
      "mode": "1"
    }
  },
  {
    "obj": {
      "type": 4,
      "start_x": 4.119499461620748,
      "start_y": 4.540299461620748,
      "start_z": 3.6452994616207475,
      "scale_x": 0.35,
      "scale_y": 0.02,
      "scale_z": 0.02,
      "mode": "0"
    }
  },
  {
    "obj": {
      "type": 1,
      "start_x": 3.569499461620748,
      "start_y": 4.540299461620748,
      "start_z": 3.6452994616207475,
      "scale_x": 0.2,
      "scale_y": 0.02,
      "scale_z": 0.2,
      "mode": "0"
    }
  },
  {
    "obj": {
      "type": 4,
      "start_x": 3.1276243270259343,
      "start_y": 4.540299461620748,
      "start_z": 3.6452994616207475,
      "scale_x": 0.24187513459481333,
      "scale_y": 0.02,
      "scale_z": 0.02,
      "mode": "0"
    }
  },
  {
    "obj": {
      "type": 1,
      "start_x": 2.6857491924311208,
      "start_y": 4.540299461620748,
      "start_z": 3.6452994616207475,
      "scale_x": 0.2,
      "scale_y": 0.02,
      "scale_z": 0.2,
      "mode": "0"
    }
  },
  {
    "obj": {
      "type": 3,
      "start_x": 2.6857491924311208,
      "start_y": 4.120299461620748,
      "start_z": 3.6452994616207475,
      "scale_x": 0.02,
      "scale_y": 0.4,
      "scale_z": 0.02,
      "mode": "0"
    }
  },
  {
    "obj": {
      "type": 1,
      "start_x": 2.6857491924311208,
      "start_y": 3.700299461620748,
      "start_z": 3.6452994616207475,
      "scale_x": 0.2,
      "scale_y": 0.02,
      "scale_z": 0.2,
      "mode": "0"
    }
  },
  {
    "obj": {
      "type": 3,
      "start_x": 2.6857491924311208,
      "start_y": 3.474124327025935,
      "start_z": 3.6452994616207475,
      "scale_x": 0.02,
      "scale_y": 0.20617513459481313,
      "scale_z": 0.02,
      "mode": "0"
    }
  },
  {
    "obj": {
      "type": 1,
      "start_x": 2.6857491924311208,
      "start_y": 3.247949192431122,
      "start_z": 3.6452994616207475,
      "scale_x": 0.2,
      "scale_y": 0.02,
      "scale_z": 0.2,
      "mode": "0"
    }
  },
  {
    "obj": {
      "type": 6,
      "start_x": 2.6857491924311208,
      "start_y": 3.247949192431122,
      "start_z": 3.243324327025934,
      "scale_x": 0.02,
      "scale_y": 0.02,
      "scale_z": 0.20197513459481317,
      "mode": "0"
    }
  },
  {
    "obj": {
      "type": 1,
      "start_x": 2.6857491924311208,
      "start_y": 3.247949192431122,
      "start_z": 2.841349192431121,
      "scale_x": 0.2,
      "scale_y": 0.02,
      "scale_z": 0.2,
      "mode": "0"
    }
  }
]