[
  {
    "obj": {
      "type": "13",
      "start_x": 2.490598923241495,
      "start_y": 2.1428684351746234,
      "start_z": 2.490598923241495,
      "scale_x": 0.20000000000000018,
      "scale_y": 0.05226951193312801,
      "scale_z": 0.20000000000000018,
      "mode": "0"
    }
  },
  {
    "obj": {
      "type": "9",
      "start_x": 2.490598923241495,
      "start_y": 2.600226664589494,
      "start_z": 2.490598923241495,
      "scale_x": 0.20000000000000018,
      "scale_y": 0.40508871748174236,
      "scale_z": 0.20000000000000018,
      "mode": "0"
    }
  },
  {
    "obj": {
      "type": "10",
      "start_x": 2.490598923241495,
      "start_y": 3.103320716945851,
      "start_z": 2.490598923241495,
      "scale_x": 0.20000000000000018,
      "scale_y": 0.09800533487461505,
      "scale_z": 0.20000000000000018,
      "mode": "0"
    }
  },
  {
    "obj": {
      "type": "11",
      "start_x": 2.490598923241495,
      "start_y": 3.2993313866950817,
      "start_z": 2.490598923241495,
      "scale_x": 0.10000000000000009,
      "scale_y": 0.09800533487461505,
      "scale_z": 0.10000000000000009,
      "mode": "0"
    }
  },
  {
    "obj": {
      "type": "4",
      "start_x": 1.7770989232414949,
      "start_y": 2.1505989232414957,
      "start_z": 2.490598923241495,
      "scale_x": 0.5135000000000001,
      "scale_y": 0.06000000000000005,
      "scale_z": 0.20000000000000018,
      "mode": "0"
    }
  },
  {
    "obj": {
      "type": "13",
      "start_x": 1.0635989232414949,
      "start_y": 2.1444672403181637,
      "start_z": 2.490598923241495,
      "scale_x": 0.19999999999999996,
      "scale_y": 0.053868317076668504,
      "scale_z": 0.20000000000000018,
      "mode": "0"
    }
  },
  {
    "obj": {
      "type": "9",
      "start_x": 1.0635989232414949,
      "start_y": 2.615815014739013,
      "start_z": 2.490598923241495,
      "scale_x": 0.19999999999999996,
      "scale_y": 0.4174794573441807,
      "scale_z": 0.20000000000000018,
      "mode": "0"
    }
  },
  {
    "obj": {
      "type": "10",
      "start_x": 1.0635989232414949,
      "start_y": 3.134297566601947,
      "start_z": 2.490598923241495,
      "scale_x": 0.19999999999999996,
      "scale_y": 0.10100309451875322,
      "scale_z": 0.20000000000000018,
      "mode": "0"
    }
  },
  {
    "obj": {
      "type": "11",
      "start_x": 1.0635989232414949,
      "start_y": 3.3363037556394533,
      "start_z": 2.490598923241495,
      "scale_x": 0.09999999999999998,
      "scale_y": 0.10100309451875344,
      "scale_z": 0.10000000000000009,
      "mode": "0"
    }
  },
  {
    "obj": {
      "type": "4",
      "start_x": 0.4077989232414949,
      "start_y": 2.1505989232414957,
      "start_z": 2.490598923241495,
      "scale_x": 0.4558,
      "scale_y": 0.06000000000000005,
      "scale_z": 0.20000000000000018,
      "mode": "0"
    }
  },
  {
    "obj": {
      "type": "14",
      "start_x": -0.24800107675850508,
      "start_y": 2.2105989232414958,
      "start_z": 2.490598923241495,
      "scale_x": 0.2,
      "scale_y": 0.11999999999999988,
      "scale_z": 0.20000000000000018,
      "mode": "0"
    }
  },
  {
    "obj": {
      "type": "14",
      "start_x": -0.24800107675850508,
      "start_y": 2.2105989232414958,
      "start_z": 2.490598923241495,
      "scale_x": 0.2,
      "scale_y": 0.11999999999999988,
      "scale_z": 0.20000000000000018,
      "mode": "0"
    }
  },
  {
    "obj": {
      "type": "1",
      "start_x": -0.24800107675850508,
      "start_y": 3.0297989232414952,
      "start_z": 2.490598923241495,
      "scale_x": 0.12,
      "scale_y": 0.33919999999999995,
      "scale_z": 0.08000000000000007,
      "mode": "0"
    }
  },
  {
    "obj": {
      "type": "13",
      "start_x": -0.24800107675850508,
      "start_y": 3.425670050340883,
      "start_z": 2.490598923241495,
      "scale_x": 0.2,
      "scale_y": 0.056671127099387375,
      "scale_z": 0.20000000000000018,
      "mode": "0"
    }
  },
  {
    "obj": {
      "type": "9",
      "start_x": -0.24800107675850508,
      "start_y": 3.9215424124605223,
      "start_z": 2.490598923241495,
      "scale_x": 0.2,
      "scale_y": 0.4392012350202521,
      "scale_z": 0.20000000000000018,
      "mode": "0"
    }
  },
  {
    "obj": {
      "type": "10",
      "start_x": -0.24800107675850508,
      "start_y": 4.467002010792125,
      "start_z": 2.490598923241495,
      "scale_x": 0.2,
      "scale_y": 0.10625836331135119,
      "scale_z": 0.20000000000000018,
      "mode": "0"
    }
  },
  {
    "obj": {
      "type": "11",
      "start_x": -0.24800107675850508,
      "start_y": 4.679518737414828,
      "start_z": 2.490598923241495,
      "scale_x": 0.1,
      "scale_y": 0.10625836331135119,
      "scale_z": 0.10000000000000009,
      "mode": "0"
    }
  },
  {
    "obj": {
      "type": "4",
      "start_x": 0.4802989232414949,
      "start_y": 3.4289989232414952,
      "start_z": 2.490598923241495,
      "scale_x": 0.5283,
      "scale_y": 0.06000000000000005,
      "scale_z": 0.20000000000000018,
      "mode": "0"
    }
  },
  {
    "obj": {
      "type": "13",
      "start_x": 1.2085989232414949,
      "start_y": 3.4323500777367917,
      "start_z": 2.490598923241495,
      "scale_x": 0.19999999999999996,
      "scale_y": 0.06335115449529738,
      "scale_z": 0.20000000000000018,
      "mode": "0"
    }
  },
  {
    "obj": {
      "type": "9",
      "start_x": 1.2085989232414949,
      "start_y": 3.986672679570644,
      "start_z": 2.490598923241495,
      "scale_x": 0.19999999999999996,
      "scale_y": 0.49097144733855513,
      "scale_z": 0.20000000000000018,
      "mode": "0"
    }
  },
  {
    "obj": {
      "type": "10",
      "start_x": 1.2085989232414949,
      "start_y": 4.596427541587882,
      "start_z": 2.490598923241495,
      "scale_x": 0.19999999999999996,
      "scale_y": 0.11878341467868303,
      "scale_z": 0.20000000000000018,
      "mode": "0"
    }
  },
  {
    "obj": {
      "type": "11",
      "start_x": 1.2085989232414949,
      "start_y": 4.833994370945248,
      "start_z": 2.490598923241495,
      "scale_x": 0.09999999999999998,
      "scale_y": 0.11878341467868259,
      "scale_z": 0.10000000000000009,
      "mode": "0"
    }
  },
  {
    "obj": {
      "type": "12",
      "start_x": 1.2085989232414949,
      "start_y": 3.4289989232414952,
      "start_z": 3.1770989232414952,
      "scale_x": 0.19999999999999996,
      "scale_y": 0.06000000000000005,
      "scale_z": 0.48649999999999993,
      "mode": "0"
    }
  },
  {
    "obj": {
      "type": "13",
      "start_x": 1.2085989232414949,
      "start_y": 3.4225103401492634,
      "start_z": 3.8635989232414953,
      "scale_x": 0.19999999999999996,
      "scale_y": 0.05351141690776817,
      "scale_z": 0.20000000000000018,
      "mode": "0"
    }
  },
  {
    "obj": {
      "type": "9",
      "start_x": 1.2085989232414949,
      "start_y": 3.890735238092236,
      "start_z": 3.8635989232414953,
      "scale_x": 0.19999999999999996,
      "scale_y": 0.41471348103520445,
      "scale_z": 0.20000000000000018,
      "mode": "0"
    }
  },
  {
    "obj": {
      "type": "10",
      "start_x": 1.2085989232414949,
      "start_y": 4.405782625829506,
      "start_z": 3.8635989232414953,
      "scale_x": 0.19999999999999996,
      "scale_y": 0.10033390670206543,
      "scale_z": 0.20000000000000018,
      "mode": "0"
    }
  },
  {
    "obj": {
      "type": "11",
      "start_x": 1.2085989232414949,
      "start_y": 4.606450439233637,
      "start_z": 3.8635989232414953,
      "scale_x": 0.09999999999999998,
      "scale_y": 0.10033390670206543,
      "scale_z": 0.10000000000000009,
      "mode": "0"
    }
  },
  {
    "obj": {
      "type": "4",
      "start_x": 2.0246989232414947,
      "start_y": 3.4289989232414952,
      "start_z": 3.8635989232414953,
      "scale_x": 0.6160999999999999,
      "scale_y": 0.06000000000000005,
      "scale_z": 0.20000000000000018,
      "mode": "0"
    }
  },
  {
    "obj": {
      "type": "13",
      "start_x": 2.8407989232414947,
      "start_y": 3.428797828589849,
      "start_z": 3.8635989232414953,
      "scale_x": 0.20000000000000018,
      "scale_y": 0.05979890534835386,
      "scale_z": 0.20000000000000018,
      "mode": "0"
    }
  },
  {
    "obj": {
      "type": "9",
      "start_x": 2.8407989232414947,
      "start_y": 3.9520382503879445,
      "start_z": 3.8635989232414953,
      "scale_x": 0.20000000000000018,
      "scale_y": 0.46344151644974163,
      "scale_z": 0.20000000000000018,
      "mode": "0"
    }
  },
  {
    "obj": {
      "type": "10",
      "start_x": 2.8407989232414947,
      "start_y": 4.52760271436585,
      "start_z": 3.8635989232414953,
      "scale_x": 0.20000000000000018,
      "scale_y": 0.11212294752816332,
      "scale_z": 0.20000000000000018,
      "mode": "0"
    }
  },
  {
    "obj": {
      "type": "11",
      "start_x": 2.8407989232414947,
      "start_y": 4.751848609422176,
      "start_z": 3.8635989232414953,
      "scale_x": 0.10000000000000009,
      "scale_y": 0.11212294752816332,
      "scale_z": 0.10000000000000009,
      "mode": "0"
    }
  },
  {
    "obj": {
      "type": "12",
      "start_x": 2.8407989232414947,
      "start_y": 3.4289989232414952,
      "start_z": 4.552698923241495,
      "scale_x": 0.20000000000000018,
      "scale_y": 0.06000000000000005,
      "scale_z": 0.48909999999999965,
      "mode": "0"
    }
  },
  {
    "obj": {
      "type": "13",
      "start_x": 2.8407989232414947,
      "start_y": 3.42871095287971,
      "start_z": 5.241798923241495,
      "scale_x": 0.20000000000000018,
      "scale_y": 0.05971202963821476,
      "scale_z": 0.20000000000000018,
      "mode": "0"
    }
  },
  {
    "obj": {
      "type": "9",
      "start_x": 2.8407989232414947,
      "start_y": 3.9511912122140895,
      "start_z": 5.241798923241495,
      "scale_x": 0.20000000000000018,
      "scale_y": 0.4627682296961648,
      "scale_z": 0.20000000000000018,
      "mode": "0"
    }
  },
  {
    "obj": {
      "type": "10",
      "start_x": 2.8407989232414947,
      "start_y": 4.525919497481907,
      "start_z": 5.241798923241495,
      "scale_x": 0.20000000000000018,
      "scale_y": 0.1119600555716529,
      "scale_z": 0.20000000000000018,
      "mode": "0"
    }
  },
  {
    "obj": {
      "type": "11",
      "start_x": 2.8407989232414947,
      "start_y": 4.749839608625213,
      "start_z": 5.241798923241495,
      "scale_x": 0.10000000000000009,
      "scale_y": 0.1119600555716529,
      "scale_z": 0.10000000000000009,
      "mode": "0"
    }
  },
  {
    "obj": {
      "type": "12",
      "start_x": 2.8407989232414947,
      "start_y": 3.4289989232414952,
      "start_z": 5.8543989232414955,
      "scale_x": 0.20000000000000018,
      "scale_y": 0.06000000000000005,
      "scale_z": 0.4126000000000003,
      "mode": "0"
    }
  },
  {
    "obj": {
      "type": "13",
      "start_x": 2.8407989232414947,
      "start_y": 3.4193381801967635,
      "start_z": 6.466998923241496,
      "scale_x": 0.20000000000000018,
      "scale_y": 0.05033925695526831,
      "scale_z": 0.20000000000000018,
      "mode": "0"
    }
  },
  {
    "obj": {
      "type": "9",
      "start_x": 2.8407989232414947,
      "start_y": 3.859806678555362,
      "start_z": 6.466998923241496,
      "scale_x": 0.20000000000000018,
      "scale_y": 0.39012924140333016,
      "scale_z": 0.20000000000000018,
      "mode": "0"
    }
  },
  {
    "obj": {
      "type": "10",
      "start_x": 2.8407989232414947,
      "start_y": 4.34432202674982,
      "start_z": 6.466998923241496,
      "scale_x": 0.20000000000000018,
      "scale_y": 0.09438610679112847,
      "scale_z": 0.20000000000000018,
      "mode": "0"
    }
  },
  {
    "obj": {
      "type": "11",
      "start_x": 2.8407989232414947,
      "start_y": 4.533094240332077,
      "start_z": 6.466998923241496,
      "scale_x": 0.10000000000000009,
      "scale_y": 0.09438610679112802,
      "scale_z": 0.10000000000000009,
      "mode": "0"
    }
  },
  {
    "obj": {
      "type": "4",
      "start_x": 1.8859989232414947,
      "start_y": 3.4289989232414952,
      "start_z": 6.466998923241496,
      "scale_x": 0.7547999999999999,
      "scale_y": 0.06000000000000005,
      "scale_z": 0.20000000000000018,
      "mode": "0"
    }
  },
  {
    "obj": {
      "type": "13",
      "start_x": 0.9311989232414948,
      "start_y": 3.4250856929286035,
      "start_z": 6.466998923241496,
      "scale_x": 0.19999999999999996,
      "scale_y": 0.05608676968710902,
      "scale_z": 0.20000000000000018,
      "mode": "0"
    }
  },
  {
    "obj": {
      "type": "9",
      "start_x": 0.9311989232414948,
      "start_y": 3.9158449276908085,
      "start_z": 6.466998923241496,
      "scale_x": 0.19999999999999996,
      "scale_y": 0.4346724650750957,
      "scale_z": 0.20000000000000018,
      "mode": "0"
    }
  },
  {
    "obj": {
      "type": "10",
      "start_x": 0.9311989232414948,
      "start_y": 4.4556800859292345,
      "start_z": 6.466998923241496,
      "scale_x": 0.19999999999999996,
      "scale_y": 0.10516269316332982,
      "scale_z": 0.20000000000000018,
      "mode": "0"
    }
  },
  {
    "obj": {
      "type": "11",
      "start_x": 0.9311989232414948,
      "start_y": 4.666005472255893,
      "start_z": 6.466998923241496,
      "scale_x": 0.09999999999999998,
      "scale_y": 0.10516269316332938,
      "scale_z": 0.10000000000000009,
      "mode": "0"
    }
  },
  {
    "obj": {
      "type": "4",
      "start_x": 0.2921989232414948,
      "start_y": 3.4289989232414952,
      "start_z": 6.466998923241496,
      "scale_x": 0.439,
      "scale_y": 0.06000000000000005,
      "scale_z": 0.20000000000000018,
      "mode": "0"
    }
  },
  {
    "obj": {
      "type": "13",
      "start_x": -0.3468010767585052,
      "start_y": 3.426643192486761,
      "start_z": 6.466998923241496,
      "scale_x": 0.2,
      "scale_y": 0.05764426924526611,
      "scale_z": 0.20000000000000018,
      "mode": "0"
    }
  },
  {
    "obj": {
      "type": "9",
      "start_x": -0.3468010767585052,
      "start_y": 3.9310305483828394,
      "start_z": 6.466998923241496,
      "scale_x": 0.2,
      "scale_y": 0.4467430866508122,
      "scale_z": 0.20000000000000018,
      "mode": "0"
    }
  },
  {
    "obj": {
      "type": "10",
      "start_x": -0.3468010767585052,
      "start_y": 4.485856639868526,
      "start_z": 6.466998923241496,
      "scale_x": 0.2,
      "scale_y": 0.10808300483487399,
      "scale_z": 0.20000000000000018,
      "mode": "0"
    }
  },
  {
    "obj": {
      "type": "11",
      "start_x": -0.3468010767585052,
      "start_y": 4.702022649538273,
      "start_z": 6.466998923241496,
      "scale_x": 0.1,
      "scale_y": 0.10808300483487399,
      "scale_z": 0.10000000000000009,
      "mode": "0"
    }
  },
  {
    "obj": {
      "type": "12",
      "start_x": -0.3468010767585052,
      "start_y": 3.4289989232414952,
      "start_z": 5.512998923241495,
      "scale_x": 0.2,
      "scale_y": 0.06000000000000005,
      "scale_z": 0.7539999999999996,
      "mode": "0"
    }
  },
  {
    "obj": {
      "type": "13",
      "start_x": -0.3468010767585052,
      "start_y": 3.4262193871734934,
      "start_z": 4.558998923241496,
      "scale_x": 0.2,
      "scale_y": 0.0572204639319982,
      "scale_z": 0.20000000000000018,
      "mode": "0"
    }
  },
  {
    "obj": {
      "type": "9",
      "start_x": -0.3468010767585052,
      "start_y": 3.926898446578478,
      "start_z": 4.558998923241496,
      "scale_x": 0.2,
      "scale_y": 0.4434585954729866,
      "scale_z": 0.20000000000000018,
      "mode": "0"
    }
  },
  {
    "obj": {
      "type": "10",
      "start_x": -0.3468010767585052,
      "start_y": 4.4776454119239615,
      "start_z": 4.558998923241496,
      "scale_x": 0.2,
      "scale_y": 0.10728836987249668,
      "scale_z": 0.20000000000000018,
      "mode": "0"
    }
  },
  {
    "obj": {
      "type": "11",
      "start_x": -0.3468010767585052,
      "start_y": 4.692222151668955,
      "start_z": 4.558998923241496,
      "scale_x": 0.1,
      "scale_y": 0.10728836987249668,
      "scale_z": 0.10000000000000009,
      "mode": "0"
    }
  },
  {
    "obj": {
      "type": "4",
      "start_x": 0.2580989232414948,
      "start_y": 3.4289989232414952,
      "start_z": 4.558998923241496,
      "scale_x": 0.4049,
      "scale_y": 0.06000000000000005,
      "scale_z": 0.20000000000000018,
      "mode": "0"
    }
  },
  {
    "obj": {
      "type": "13",
      "start_x": 0.8629989232414947,
      "start_y": 3.4248021950805407,
      "start_z": 4.558998923241496,
      "scale_x": 0.19999999999999996,
      "scale_y": 0.05580327183904643,
      "scale_z": 0.20000000000000018,
      "mode": "0"
    }
  },
  {
    "obj": {
      "type": "9",
      "start_x": 0.8629989232414947,
      "start_y": 3.9130808236721975,
      "start_z": 4.558998923241496,
      "scale_x": 0.19999999999999996,
      "scale_y": 0.4324753567526103,
      "scale_z": 0.20000000000000018,
      "mode": "0"
    }
  },
  {
    "obj": {
      "type": "10",
      "start_x": 0.8629989232414947,
      "start_y": 4.450187315123021,
      "start_z": 4.558998923241496,
      "scale_x": 0.19999999999999996,
      "scale_y": 0.1046311346982125,
      "scale_z": 0.20000000000000018,
      "mode": "0"
    }
  },
  {
    "obj": {
      "type": "11",
      "start_x": 0.8629989232414947,
      "start_y": 4.659449584519445,
      "start_z": 4.558998923241496,
      "scale_x": 0.09999999999999998,
      "scale_y": 0.10463113469821206,
      "scale_z": 0.10000000000000009,
      "mode": "0"
    }
  },
  {
    "obj": {
      "type": "12",
      "start_x": 0.8629989232414947,
      "start_y": 3.4289989232414952,
      "start_z": 5.238698923241496,
      "scale_x": 0.19999999999999996,
      "scale_y": 0.06000000000000005,
      "scale_z": 0.47970000000000024,
      "mode": "0"
    }
  },
  {
    "obj": {
      "type": "14",
      "start_x": 0.8629989232414947,
      "start_y": 3.4889989232414953,
      "start_z": 5.918398923241496,
      "scale_x": 0.19999999999999996,
      "scale_y": 0.11999999999999988,
      "scale_z": 0.20000000000000018,
      "mode": "0"
    }
  },
  {
    "obj": {
      "type": "14",
      "start_x": 0.8629989232414947,
      "start_y": 3.4889989232414953,
      "start_z": 5.918398923241496,
      "scale_x": 0.19999999999999996,
      "scale_y": 0.11999999999999988,
      "scale_z": 0.20000000000000018,
      "mode": "0"
    }
  },
  {
    "obj": {
      "type": "1",
      "start_x": 0.8629989232414947,
      "start_y": 4.585598923241495,
      "start_z": 5.918398923241496,
      "scale_x": 0.11999999999999997,
      "scale_y": 0.6166,
      "scale_z": 0.08000000000000007,
      "mode": "0"
    }
  },
  {
    "obj": {
      "type": "13",
      "start_x": 0.8629989232414947,
      "start_y": 5.25409115808208,
      "start_z": 5.918398923241496,
      "scale_x": 0.19999999999999996,
      "scale_y": 0.05189223484058525,
      "scale_z": 0.20000000000000018,
      "mode": "0"
    }
  },
  {
    "obj": {
      "type": "9",
      "start_x": 0.8629989232414947,
      "start_y": 5.7081482129372,
      "start_z": 5.918398923241496,
      "scale_x": 0.19999999999999996,
      "scale_y": 0.402164820014534,
      "scale_z": 0.20000000000000018,
      "mode": "0"
    }
  },
  {
    "obj": {
      "type": "10",
      "start_x": 0.8629989232414947,
      "start_y": 6.207610973277831,
      "start_z": 5.918398923241496,
      "scale_x": 0.19999999999999996,
      "scale_y": 0.09729794032609718,
      "scale_z": 0.20000000000000018,
      "mode": "0"
    }
  },
  {
    "obj": {
      "type": "11",
      "start_x": 0.8629989232414947,
      "start_y": 6.402206853930025,
      "start_z": 5.918398923241496,
      "scale_x": 0.09999999999999998,
      "scale_y": 0.09729794032609718,
      "scale_z": 0.10000000000000009,
      "mode": "0"
    }
  },
  {
    "obj": {
      "type": "9",
      "start_x": 0.1811978464829906,
      "start_y": 0.02199784648299058,
      "start_z": 0.1811978464829906,
      "scale_x": 0.2,
      "scale_y": 0.3592,
      "scale_z": 0.2,
      "mode": "0"
    }
  },
  {
    "obj": {
      "type": "9",
      "start_x": 0.1811978464829906,
      "start_y": -0.18210215351700942,
      "start_z": 0.1811978464829906,
      "scale_x": 0.2,
      "scale_y": 0.5633,
      "scale_z": 0.2,
      "mode": "0"
    }
  },
  {
    "obj": {
      "type": "1",
      "start_x": 0.1811978464829906,
      "start_y": -0.06930215351700941,
      "start_z": 0.1811978464829906,
      "scale_x": 0.12,
      "scale_y": 0.4505,
      "scale_z": 0.08000000000000002,
      "mode": "0"
    }
  },
  {
    "obj": {
      "type": "1",
      "start_x": 0.1811978464829906,
      "start_y": -0.3488021535170094,
      "start_z": 0.1811978464829906,
      "scale_x": 0.12,
      "scale_y": 0.73,
      "scale_z": 0.08000000000000002,
      "mode": "0"
    }
  },
  {
    "obj": {
      "type": "14",
      "start_x": 0.1811978464829906,
      "start_y": -1.5588021535170093,
      "start_z": 0.1811978464829906,
      "scale_x": 0.2,
      "scale_y": 0.12,
      "scale_z": 0.2,
      "mode": "0"
    }
  },
  {
    "obj": {
      "type": "14",
      "start_x": 0.1811978464829906,
      "start_y": -1.5588021535170093,
      "start_z": 0.1811978464829906,
      "scale_x": 0.2,
      "scale_y": 0.12,
      "scale_z": 0.2,
      "mode": "0"
    }
  },
  {
    "obj": {
      "type": "4",
      "start_x": 0.9155978464829906,
      "start_y": -1.6188021535170094,
      "start_z": 0.1811978464829906,
      "scale_x": 0.5344,
      "scale_y": 0.06000000000000005,
      "scale_z": 0.2,
      "mode": "0"
    }
  },
  {
    "obj": {
      "type": "13",
      "start_x": 1.6499978464829905,
      "start_y": -1.6148099637827515,
      "start_z": 0.1811978464829906,
      "scale_x": 0.19999999999999996,
      "scale_y": 0.06399218973425802,
      "scale_z": 0.2,
      "mode": "0"
    }
  },
  {
    "obj": {
      "type": "9",
      "start_x": 1.6499978464829905,
      "start_y": -1.0548783036079938,
      "start_z": 0.1811978464829906,
      "scale_x": 0.19999999999999996,
      "scale_y": 0.4959394704404996,
      "scale_z": 0.2,
      "mode": "0"
    }
  },
  {
    "obj": {
      "type": "10",
      "start_x": 1.6499978464829905,
      "start_y": -0.4389534774157604,
      "start_z": 0.1811978464829906,
      "scale_x": 0.19999999999999996,
      "scale_y": 0.11998535575173386,
      "scale_z": 0.2,
      "mode": "0"
    }
  },
  {
    "obj": {
      "type": "11",
      "start_x": 1.6499978464829905,
      "start_y": -0.1989827659122928,
      "start_z": 0.1811978464829906,
      "scale_x": 0.09999999999999998,
      "scale_y": 0.11998535575173375,
      "scale_z": 0.1,
      "mode": "0"
    }
  },
  {
    "obj": {
      "type": "9",
      "start_x": 1.6499978464829905,
      "start_y": -1.9003021535170095,
      "start_z": 0.1811978464829906,
      "scale_x": 0.19999999999999996,
      "scale_y": 0.22150000000000003,
      "scale_z": 0.2,
      "mode": "0"
    }
  },
  {
    "obj": {
      "type": "14",
      "start_x": 1.6499978464829905,
      "start_y": -2.601802153517009,
      "start_z": 0.1811978464829906,
      "scale_x": 0.19999999999999996,
      "scale_y": 0.11999999999999988,
      "scale_z": 0.2,
      "mode": "0"
    }
  },
  {
    "obj": {
      "type": "14",
      "start_x": 1.6499978464829905,
      "start_y": -2.601802153517009,
      "start_z": 0.1811978464829906,
      "scale_x": 0.19999999999999996,
      "scale_y": 0.11999999999999988,
      "scale_z": 0.2,
      "mode": "0"
    }
  },
  {
    "obj": {
      "type": "4",
      "start_x": 2.4017978464829906,
      "start_y": -2.661802153517009,
      "start_z": 0.1811978464829906,
      "scale_x": 0.5518000000000001,
      "scale_y": 0.06000000000000005,
      "scale_z": 0.2,
      "mode": "0"
    }
  },
  {
    "obj": {
      "type": "13",
      "start_x": 3.153597846482991,
      "start_y": -2.664723348138335,
      "start_z": 0.1811978464829906,
      "scale_x": 0.20000000000000018,
      "scale_y": 0.05707880537867416,
      "scale_z": 0.2,
      "mode": "0"
    }
  },
  {
    "obj": {
      "type": "9",
      "start_x": 3.153597846482991,
      "start_y": -2.165283801074936,
      "start_z": 0.1811978464829906,
      "scale_x": 0.20000000000000018,
      "scale_y": 0.4423607416847253,
      "scale_z": 0.2,
      "mode": "0"
    }
  },
  {
    "obj": {
      "type": "10",
      "start_x": 3.153597846482991,
      "start_y": -1.615900299305196,
      "start_z": 0.1811978464829906,
      "scale_x": 0.20000000000000018,
      "scale_y": 0.1070227600850141,
      "scale_z": 0.2,
      "mode": "0"
    }
  },
  {
    "obj": {
      "type": "11",
      "start_x": 3.153597846482991,
      "start_y": -1.4018547791351679,
      "start_z": 0.1811978464829906,
      "scale_x": 0.10000000000000009,
      "scale_y": 0.10702276008501421,
      "scale_z": 0.1,
      "mode": "0"
    }
  },
  {
    "obj": {
      "type": "4",
      "start_x": 3.960997846482991,
      "start_y": -2.661802153517009,
      "start_z": 0.1811978464829906,
      "scale_x": 0.6074000000000002,
      "scale_y": 0.06000000000000005,
      "scale_z": 0.2,
      "mode": "0"
    }
  },
  {
    "obj": {
      "type": "13",
      "start_x": 4.7683978464829915,
      "start_y": -2.6606408171764953,
      "start_z": 0.1811978464829906,
      "scale_x": 0.20000000000000018,
      "scale_y": 0.061161336340513905,
      "scale_z": 0.2,
      "mode": "0"
    }
  },
  {
    "obj": {
      "type": "9",
      "start_x": 4.7683978464829915,
      "start_y": -2.1254791241969992,
      "start_z": 0.1811978464829906,
      "scale_x": 0.20000000000000018,
      "scale_y": 0.474000356638982,
      "scale_z": 0.2,
      "mode": "0"
    }
  },
  {
    "obj": {
      "type": "10",
      "start_x": 4.7683978464829915,
      "start_y": -1.536801261919554,
      "start_z": 0.1811978464829906,
      "scale_x": 0.20000000000000018,
      "scale_y": 0.11467750563846346,
      "scale_z": 0.2,
      "mode": "0"
    }
  },
  {
    "obj": {
      "type": "11",
      "start_x": 4.7683978464829915,
      "start_y": -1.307446250642627,
      "start_z": 0.1811978464829906,
      "scale_x": 0.10000000000000009,
      "scale_y": 0.11467750563846346,
      "scale_z": 0.1,
      "mode": "0"
    }
  },
  {
    "obj": {
      "type": "12",
      "start_x": 4.7683978464829915,
      "start_y": -2.661802153517009,
      "start_z": 1.0941978464829907,
      "scale_x": 0.20000000000000018,
      "scale_y": 0.06000000000000005,
      "scale_z": 0.7130000000000001,
      "mode": "0"
    }
  },
  {
    "obj": {
      "type": "13",
      "start_x": 4.7683978464829915,
      "start_y": -2.6609006929824632,
      "start_z": 2.007197846482991,
      "scale_x": 0.20000000000000018,
      "scale_y": 0.060901460534545704,
      "scale_z": 0.20000000000000007,
      "mode": "0"
    }
  },
  {
    "obj": {
      "type": "9",
      "start_x": 4.7683978464829915,
      "start_y": -2.128012913305189,
      "start_z": 2.007197846482991,
      "scale_x": 0.20000000000000018,
      "scale_y": 0.4719863191427288,
      "scale_z": 0.20000000000000007,
      "mode": "0"
    }
  },
  {
    "obj": {
      "type": "10",
      "start_x": 4.7683978464829915,
      "start_y": -1.541836355660187,
      "start_z": 2.007197846482991,
      "scale_x": 0.20000000000000018,
      "scale_y": 0.11419023850227317,
      "scale_z": 0.20000000000000007,
      "mode": "0"
    }
  },
  {
    "obj": {
      "type": "11",
      "start_x": 4.7683978464829915,
      "start_y": -1.3134558786556405,
      "start_z": 2.007197846482991,
      "scale_x": 0.10000000000000009,
      "scale_y": 0.11419023850227317,
      "scale_z": 0.10000000000000003,
      "mode": "0"
    }
  },
  {
    "obj": {
      "type": "9",
      "start_x": 4.7683978464829915,
      "start_y": -3.0525021535170094,
      "start_z": 2.007197846482991,
      "scale_x": 0.20000000000000018,
      "scale_y": 0.3307000000000002,
      "scale_z": 0.20000000000000007,
      "mode": "0"
    }
  },
  {
    "obj": {
      "type": "14",
      "start_x": 4.7683978464829915,
      "start_y": -3.863202153517009,
      "start_z": 2.007197846482991,
      "scale_x": 0.20000000000000018,
      "scale_y": 0.11999999999999988,
      "scale_z": 0.20000000000000007,
      "mode": "0"
    }
  },
  {
    "obj": {
      "type": "14",
      "start_x": 4.7683978464829915,
      "start_y": -3.863202153517009,
      "start_z": 2.007197846482991,
      "scale_x": 0.20000000000000018,
      "scale_y": 0.11999999999999988,
      "scale_z": 0.20000000000000007,
      "mode": "0"
    }
  },
  {
    "obj": {
      "type": "4",
      "start_x": 5.503497846482992,
      "start_y": -3.923202153517009,
      "start_z": 2.007197846482991,
      "scale_x": 0.5350999999999999,
      "scale_y": 0.06000000000000005,
      "scale_z": 0.20000000000000007,
      "mode": "0"
    }
  },
  {
    "obj": {
      "type": "13",
      "start_x": 6.238597846482992,
      "start_y": -3.9200285520233273,
      "start_z": 2.007197846482991,
      "scale_x": 0.20000000000000018,
      "scale_y": 0.0631736014936819,
      "scale_z": 0.20000000000000007,
      "mode": "0"
    }
  },
  {
    "obj": {
      "type": "9",
      "start_x": 6.238597846482992,
      "start_y": -3.367259538953611,
      "start_z": 2.007197846482991,
      "scale_x": 0.20000000000000018,
      "scale_y": 0.4895954115760346,
      "scale_z": 0.20000000000000007,
      "mode": "0"
    }
  },
  {
    "obj": {
      "type": "10",
      "start_x": 6.238597846482992,
      "start_y": -2.7592136245769225,
      "start_z": 2.007197846482991,
      "scale_x": 0.20000000000000018,
      "scale_y": 0.1184505028006535,
      "scale_z": 0.20000000000000007,
      "mode": "0"
    }
  },
  {
    "obj": {
      "type": "11",
      "start_x": 6.238597846482992,
      "start_y": -2.522312618975616,
      "start_z": 2.007197846482991,
      "scale_x": 0.10000000000000009,
      "scale_y": 0.1184505028006535,
      "scale_z": 0.10000000000000003,
      "mode": "0"
    }
  },
  {
    "obj": {
      "type": "9",
      "start_x": 6.238597846482992,
      "start_y": -4.187502153517009,
      "start_z": 2.007197846482991,
      "scale_x": 0.20000000000000018,
      "scale_y": 0.20429999999999993,
      "scale_z": 0.20000000000000007,
      "mode": "0"
    }
  },
  {
    "obj": {
      "type": "14",
      "start_x": 6.238597846482992,
      "start_y": -4.871802153517009,
      "start_z": 2.007197846482991,
      "scale_x": 0.20000000000000018,
      "scale_y": 0.1200000000000001,
      "scale_z": 0.20000000000000007,
      "mode": "0"
    }
  },
  {
    "obj": {
      "type": "14",
      "start_x": 6.238597846482992,
      "start_y": -4.871802153517009,
      "start_z": 2.007197846482991,
      "scale_x": 0.20000000000000018,
      "scale_y": 0.1200000000000001,
      "scale_z": 0.20000000000000007,
      "mode": "0"
    }
  },
  {
    "obj": {
      "type": "12",
      "start_x": 6.238597846482992,
      "start_y": -4.931802153517008,
      "start_z": 2.890097846482991,
      "scale_x": 0.20000000000000018,
      "scale_y": 0.06000000000000005,
      "scale_z": 0.6829000000000001,
      "mode": "0"
    }
  },
  {
    "obj": {
      "type": "13",
      "start_x": 6.238597846482992,
      "start_y": -4.937000339963028,
      "start_z": 3.7729978464829914,
      "scale_x": 0.20000000000000018,
      "scale_y": 0.05480181355398139,
      "scale_z": 0.20000000000000018,
      "mode": "0"
    }
  },
  {
    "obj": {
      "type": "9",
      "start_x": 6.238597846482992,
      "start_y": -4.4574844713656905,
      "start_z": 3.7729978464829914,
      "scale_x": 0.20000000000000018,
      "scale_y": 0.424714055043355,
      "scale_z": 0.20000000000000018,
      "mode": "0"
    }
  },
  {
    "obj": {
      "type": "10",
      "start_x": 6.238597846482992,
      "start_y": -3.9300170159086205,
      "start_z": 3.7729978464829914,
      "scale_x": 0.20000000000000018,
      "scale_y": 0.10275340041371517,
      "scale_z": 0.20000000000000018,
      "mode": "0"
    }
  },
  {
    "obj": {
      "type": "11",
      "start_x": 6.238597846482992,
      "start_y": -3.7245102150811906,
      "start_z": 3.7729978464829914,
      "scale_x": 0.10000000000000009,
      "scale_y": 0.10275340041371495,
      "scale_z": 0.10000000000000009,
      "mode": "0"
    }
  },
  {
    "obj": {
      "type": "12",
      "start_x": 6.238597846482992,
      "start_y": -4.931802153517008,
      "start_z": 4.716397846482992,
      "scale_x": 0.20000000000000018,
      "scale_y": 0.06000000000000005,
      "scale_z": 0.7434000000000001,
      "mode": "0"
    }
  },
  {
    "obj": {
      "type": "13",
      "start_x": 6.238597846482992,
      "start_y": -4.943225203065336,
      "start_z": 5.659797846482992,
      "scale_x": 0.20000000000000018,
      "scale_y": 0.04857695045167265,
      "scale_z": 0.20000000000000018,
      "mode": "0"
    }
  },
  {
    "obj": {
      "type": "9",
      "start_x": 6.238597846482992,
      "start_y": -4.5181768866132,
      "start_z": 5.659797846482992,
      "scale_x": 0.20000000000000018,
      "scale_y": 0.37647136600046327,
      "scale_z": 0.20000000000000018,
      "mode": "0"
    }
  },
  {
    "obj": {
      "type": "10",
      "start_x": 6.238597846482992,
      "start_y": -4.050623738515851,
      "start_z": 5.659797846482992,
      "scale_x": 0.20000000000000018,
      "scale_y": 0.09108178209688633,
      "scale_z": 0.20000000000000018,
      "mode": "0"
    }
  },
  {
    "obj": {
      "type": "11",
      "start_x": 6.238597846482992,
      "start_y": -3.868460174322078,
      "start_z": 5.659797846482992,
      "scale_x": 0.10000000000000009,
      "scale_y": 0.09108178209688633,
      "scale_z": 0.10000000000000009,
      "mode": "0"
    }
  },
  {
    "obj": {
      "type": "9",
      "start_x": 6.238597846482992,
      "start_y": -5.677802153517009,
      "start_z": 5.659797846482992,
      "scale_x": 0.20000000000000018,
      "scale_y": 0.6859999999999999,
      "scale_z": 0.20000000000000018,
      "mode": "0"
    }
  },
  {
    "obj": {
      "type": "14",
      "start_x": 6.238597846482992,
      "start_y": -6.843802153517008,
      "start_z": 5.659797846482992,
      "scale_x": 0.20000000000000018,
      "scale_y": 0.1200000000000001,
      "scale_z": 0.20000000000000018,
      "mode": "0"
    }
  },
  {
    "obj": {
      "type": "14",
      "start_x": 6.238597846482992,
      "start_y": -6.843802153517008,
      "start_z": 5.659797846482992,
      "scale_x": 0.20000000000000018,
      "scale_y": 0.1200000000000001,
      "scale_z": 0.20000000000000018,
      "mode": "0"
    }
  },
  {
    "obj": {
      "type": "12",
      "start_x": 6.238597846482992,
      "start_y": -6.903802153517008,
      "start_z": 6.270597846482993,
      "scale_x": 0.20000000000000018,
      "scale_y": 0.06000000000000005,
      "scale_z": 0.41080000000000005,
      "mode": "0"
    }
  },
  {
    "obj": {
      "type": "13",
      "start_x": 6.238597846482992,
      "start_y": -6.9126574844660755,
      "start_z": 6.881397846482993,
      "scale_x": 0.20000000000000018,
      "scale_y": 0.05114466905093318,
      "scale_z": 0.20000000000000018,
      "mode": "0"
    }
  },
  {
    "obj": {
      "type": "9",
      "start_x": 6.238597846482992,
      "start_y": -6.46514163027041,
      "start_z": 6.881397846482993,
      "scale_x": 0.20000000000000018,
      "scale_y": 0.3963711851447318,
      "scale_z": 0.20000000000000018,
      "mode": "0"
    }
  },
  {
    "obj": {
      "type": "10",
      "start_x": 6.238597846482992,
      "start_y": -5.972874190655178,
      "start_z": 6.881397846482993,
      "scale_x": 0.20000000000000018,
      "scale_y": 0.09589625447049999,
      "scale_z": 0.20000000000000018,
      "mode": "0"
    }
  },
  {
    "obj": {
      "type": "11",
      "start_x": 6.238597846482992,
      "start_y": -5.781081681714179,
      "start_z": 6.881397846482993,
      "scale_x": 0.10000000000000009,
      "scale_y": 0.09589625447049954,
      "scale_z": 0.10000000000000009,
      "mode": "0"
    }
  },
  {
    "obj": {
      "type": "4",
      "start_x": 6.909897846482992,
      "start_y": -6.903802153517008,
      "start_z": 6.881397846482993,
      "scale_x": 0.4713000000000003,
      "scale_y": 0.06000000000000005,
      "scale_z": 0.20000000000000018,
      "mode": "0"
    }
  },
  {
    "obj": {
      "type": "13",
      "start_x": 7.5811978464829926,
      "start_y": -6.914297325086603,
      "start_z": 6.881397846482993,
      "scale_x": 0.20000000000000018,
      "scale_y": 0.049504828430404935,
      "scale_z": 0.20000000000000018,
      "mode": "0"
    }
  },
  {
    "obj": {
      "type": "9",
      "start_x": 7.5811978464829926,
      "start_y": -6.481130076320562,
      "start_z": 6.881397846482993,
      "scale_x": 0.20000000000000018,
      "scale_y": 0.3836624203356367,
      "scale_z": 0.20000000000000018,
      "mode": "0"
    }
  },
  {
    "obj": {
      "type": "10",
      "start_x": 7.5811978464829926,
      "start_y": -6.004646102677916,
      "start_z": 6.881397846482993,
      "scale_x": 0.20000000000000018,
      "scale_y": 0.09282155330700892,
      "scale_z": 0.20000000000000018,
      "mode": "0"
    }
  },
  {
    "obj": {
      "type": "11",
      "start_x": 7.5811978464829926,
      "start_y": -5.819002996063898,
      "start_z": 6.881397846482993,
      "scale_x": 0.10000000000000009,
      "scale_y": 0.09282155330700892,
      "scale_z": 0.10000000000000009,
      "mode": "0"
    }
  },
  {
    "obj": {
      "type": "1",
      "start_x": 7.5811978464829926,
      "start_y": -7.365502153517008,
      "start_z": 6.881397846482993,
      "scale_x": 0.1200000000000001,
      "scale_y": 0.40169999999999995,
      "scale_z": 0.08000000000000007,
      "mode": "0"
    }
  },
  {
    "obj": {
      "type": "14",
      "start_x": 7.5811978464829926,
      "start_y": -8.247202153517009,
      "start_z": 6.881397846482993,
      "scale_x": 0.20000000000000018,
      "scale_y": 0.1200000000000001,
      "scale_z": 0.20000000000000018,
      "mode": "0"
    }
  },
  {
    "obj": {
      "type": "14",
      "start_x": 7.5811978464829926,
      "start_y": -8.247202153517009,
      "start_z": 6.881397846482993,
      "scale_x": 0.20000000000000018,
      "scale_y": 0.1200000000000001,
      "scale_z": 0.20000000000000018,
      "mode": "0"
    }
  },
  {
    "obj": {
      "type": "4",
      "start_x": 6.820497846482993,
      "start_y": -8.307202153517009,
      "start_z": 6.881397846482993,
      "scale_x": 0.5606999999999998,
      "scale_y": 0.0600000000000005,
      "scale_z": 0.20000000000000018,
      "mode": "0"
    }
  },
  {
    "obj": {
      "type": "13",
      "start_x": 6.059797846482993,
      "start_y": -8.307548428348763,
      "start_z": 6.881397846482993,
      "scale_x": 0.20000000000000018,
      "scale_y": 0.05965372516824541,
      "scale_z": 0.20000000000000018,
      "mode": "0"
    }
  },
  {
    "obj": {
      "type": "9",
      "start_x": 6.059797846482993,
      "start_y": -7.785578333126621,
      "start_z": 6.881397846482993,
      "scale_x": 0.20000000000000018,
      "scale_y": 0.4623163700538986,
      "scale_z": 0.20000000000000018,
      "mode": "0"
    }
  },
  {
    "obj": {
      "type": "10",
      "start_x": 6.059797846482993,
      "start_y": -7.2114112283822625,
      "start_z": 6.881397846482993,
      "scale_x": 0.20000000000000018,
      "scale_y": 0.11185073469045914,
      "scale_z": 0.20000000000000018,
      "mode": "0"
    }
  },
  {
    "obj": {
      "type": "11",
      "start_x": 6.059797846482993,
      "start_y": -6.987709759001344,
      "start_z": 6.881397846482993,
      "scale_x": 0.10000000000000009,
      "scale_y": 0.11185073469045959,
      "scale_z": 0.10000000000000009,
      "mode": "0"
    }
  },
  {
    "obj": {
      "type": "12",
      "start_x": 6.059797846482993,
      "start_y": -8.307202153517009,
      "start_z": 7.618297846482993,
      "scale_x": 0.20000000000000018,
      "scale_y": 0.0600000000000005,
      "scale_z": 0.5369000000000002,
      "mode": "0"
    }
  },
  {
    "obj": {
      "type": "13",
      "start_x": 6.059797846482993,
      "start_y": -8.312006872827723,
      "start_z": 8.355197846482993,
      "scale_x": 0.20000000000000018,
      "scale_y": 0.055195280689285475,
      "scale_z": 0.1999999999999993,
      "mode": "0"
    }
  },
  {
    "obj": {
      "type": "9",
      "start_x": 6.059797846482993,
      "start_y": -7.829048166796472,
      "start_z": 8.355197846482993,
      "scale_x": 0.20000000000000018,
      "scale_y": 0.4277634253419662,
      "scale_z": 0.1999999999999993,
      "mode": "0"
    }
  },
  {
    "obj": {
      "type": "10",
      "start_x": 6.059797846482993,
      "start_y": -7.297793590162096,
      "start_z": 8.355197846482993,
      "scale_x": 0.20000000000000018,
      "scale_y": 0.10349115129241104,
      "scale_z": 0.1999999999999993,
      "mode": "0"
    }
  },
  {
    "obj": {
      "type": "11",
      "start_x": 6.059797846482993,
      "start_y": -7.090811287577273,
      "start_z": 8.355197846482993,
      "scale_x": 0.10000000000000009,
      "scale_y": 0.10349115129241104,
      "scale_z": 0.09999999999999964,
      "mode": "0"
    }
  },
  {
    "obj": {
      "type": "9",
      "start_x": 6.059797846482993,
      "start_y": -9.16360215351701,
      "start_z": 8.355197846482993,
      "scale_x": 0.20000000000000018,
      "scale_y": 0.7964000000000002,
      "scale_z": 0.1999999999999993,
      "mode": "0"
    }
  },
  {
    "obj": {
      "type": "14",
      "start_x": 6.059797846482993,
      "start_y": -10.44000215351701,
      "start_z": 8.355197846482993,
      "scale_x": 0.20000000000000018,
      "scale_y": 0.1200000000000001,
      "scale_z": 0.1999999999999993,
      "mode": "0"
    }
  },
  {
    "obj": {
      "type": "14",
      "start_x": 6.059797846482993,
      "start_y": -10.44000215351701,
      "start_z": 8.355197846482993,
      "scale_x": 0.20000000000000018,
      "scale_y": 0.1200000000000001,
      "scale_z": 0.1999999999999993,
      "mode": "0"
    }
  },
  {
    "obj": {
      "type": "1",
      "start_x": 6.059797846482993,
      "start_y": -11.318902153517012,
      "start_z": 8.355197846482993,
      "scale_x": 0.1200000000000001,
      "scale_y": 0.7589000000000006,
      "scale_z": 0.07999999999999972,
      "mode": "0"
    }
  },
  {
    "obj": {
      "type": "14",
      "start_x": 6.059797846482993,
      "start_y": -12.557802153517013,
      "start_z": 8.355197846482993,
      "scale_x": 0.20000000000000018,
      "scale_y": 0.1200000000000001,
      "scale_z": 0.1999999999999993,
      "mode": "0"
    }
  },
  {
    "obj": {
      "type": "14",
      "start_x": 6.059797846482993,
      "start_y": -12.557802153517013,
      "start_z": 8.355197846482993,
      "scale_x": 0.20000000000000018,
      "scale_y": 0.1200000000000001,
      "scale_z": 0.1999999999999993,
      "mode": "0"
    }
  },
  {
    "obj": {
      "type": "4",
      "start_x": 5.430497846482993,
      "start_y": -12.617802153517014,
      "start_z": 8.355197846482993,
      "scale_x": 0.42929999999999957,
      "scale_y": 0.0600000000000005,
      "scale_z": 0.1999999999999993,
      "mode": "0"
    }
  },
  {
    "obj": {
      "type": "14",
      "start_x": 4.801197846482993,
      "start_y": -12.557802153517013,
      "start_z": 8.355197846482993,
      "scale_x": 0.20000000000000018,
      "scale_y": 0.1200000000000001,
      "scale_z": 0.1999999999999993,
      "mode": "0"
    }
  },
  {
    "obj": {
      "type": "14",
      "start_x": 4.801197846482993,
      "start_y": -12.557802153517013,
      "start_z": 8.355197846482993,
      "scale_x": 0.20000000000000018,
      "scale_y": 0.1200000000000001,
      "scale_z": 0.1999999999999993,
      "mode": "0"
    }
  },
  {
    "obj": {
      "type": "1",
      "start_x": 4.801197846482993,
      "start_y": -11.622002153517013,
      "start_z": 8.355197846482993,
      "scale_x": 0.1200000000000001,
      "scale_y": 0.4558,
      "scale_z": 0.07999999999999972,
      "mode": "0"
    }
  },
  {
    "obj": {
      "type": "13",
      "start_x": 4.801197846482993,
      "start_y": -11.108678920400948,
      "start_z": 8.355197846482993,
      "scale_x": 0.20000000000000018,
      "scale_y": 0.057523233116065775,
      "scale_z": 0.1999999999999993,
      "mode": "0"
    }
  },
  {
    "obj": {
      "type": "9",
      "start_x": 4.801197846482993,
      "start_y": -10.605350630635371,
      "start_z": 8.355197846482993,
      "scale_x": 0.20000000000000018,
      "scale_y": 0.44580505664951087,
      "scale_z": 0.1999999999999993,
      "mode": "0"
    }
  },
  {
    "obj": {
      "type": "10",
      "start_x": 4.801197846482993,
      "start_y": -10.051689511893237,
      "start_z": 8.355197846482993,
      "scale_x": 0.20000000000000018,
      "scale_y": 0.10785606209262344,
      "scale_z": 0.1999999999999993,
      "mode": "0"
    }
  },
  {
    "obj": {
      "type": "11",
      "start_x": 4.801197846482993,
      "start_y": -9.835977387707988,
      "start_z": 8.355197846482993,
      "scale_x": 0.10000000000000009,
      "scale_y": 0.10785606209262344,
      "scale_z": 0.09999999999999964,
      "mode": "0"
    }
  },
  {
    "obj": {
      "type": "12",
      "start_x": 4.801197846482993,
      "start_y": -11.106202153517012,
      "start_z": 9.142697846482992,
      "scale_x": 0.20000000000000018,
      "scale_y": 0.0600000000000005,
      "scale_z": 0.5875000000000004,
      "mode": "0"
    }
  },
  {
    "obj": {
      "type": "14",
      "start_x": 4.801197846482993,
      "start_y": -11.046202153517012,
      "start_z": 9.930197846482992,
      "scale_x": 0.20000000000000018,
      "scale_y": 0.1200000000000001,
      "scale_z": 0.1999999999999993,
      "mode": "0"
    }
  },
  {
    "obj": {
      "type": "14",
      "start_x": 4.801197846482993,
      "start_y": -11.046202153517012,
      "start_z": 9.930197846482992,
      "scale_x": 0.20000000000000018,
      "scale_y": 0.1200000000000001,
      "scale_z": 0.1999999999999993,
      "mode": "0"
    }
  },
  {
    "obj": {
      "type": "1",
      "start_x": 4.801197846482993,
      "start_y": -10.129502153517011,
      "start_z": 9.930197846482992,
      "scale_x": 0.1200000000000001,
      "scale_y": 0.4367000000000001,
      "scale_z": 0.07999999999999972,
      "mode": "0"
    }
  },
  {
    "obj": {
      "type": "14",
      "start_x": 4.801197846482993,
      "start_y": -9.57280215351701,
      "start_z": 9.930197846482992,
      "scale_x": 0.20000000000000018,
      "scale_y": 0.1200000000000001,
      "scale_z": 0.1999999999999993,
      "mode": "0"
    }
  },
  {
    "obj": {
      "type": "14",
      "start_x": 4.801197846482993,
      "start_y": -9.57280215351701,
      "start_z": 9.930197846482992,
      "scale_x": 0.20000000000000018,
      "scale_y": 0.1200000000000001,
      "scale_z": 0.1999999999999993,
      "mode": "0"
    }
  },
  {
    "obj": {
      "type": "1",
      "start_x": 4.801197846482993,
      "start_y": -8.35510215351701,
      "start_z": 9.930197846482992,
      "scale_x": 0.1200000000000001,
      "scale_y": 0.7377000000000002,
      "scale_z": 0.07999999999999972,
      "mode": "0"
    }
  },
  {
    "obj": {
      "type": "14",
      "start_x": 4.801197846482993,
      "start_y": -7.497402153517009,
      "start_z": 9.930197846482992,
      "scale_x": 0.20000000000000018,
      "scale_y": 0.1200000000000001,
      "scale_z": 0.1999999999999993,
      "mode": "0"
    }
  },
  {
    "obj": {
      "type": "14",
      "start_x": 4.801197846482993,
      "start_y": -7.497402153517009,
      "start_z": 9.930197846482992,
      "scale_x": 0.20000000000000018,
      "scale_y": 0.1200000000000001,
      "scale_z": 0.1999999999999993,
      "mode": "0"
    }
  },
  {
    "obj": {
      "type": "1",
      "start_x": 4.801197846482993,
      "start_y": -6.79660215351701,
      "start_z": 9.930197846482992,
      "scale_x": 0.1200000000000001,
      "scale_y": 0.22079999999999966,
      "scale_z": 0.07999999999999972,
      "mode": "0"
    }
  },
  {
    "obj": {
      "type": "13",
      "start_x": 4.801197846482993,
      "start_y": -6.515554058719218,
      "start_z": 9.930197846482992,
      "scale_x": 0.20000000000000018,
      "scale_y": 0.060248094797792806,
      "scale_z": 0.1999999999999993,
      "mode": "0"
    }
  },
  {
    "obj": {
      "type": "9",
      "start_x": 4.801197846482993,
      "start_y": -5.988383229238529,
      "start_z": 9.930197846482992,
      "scale_x": 0.20000000000000018,
      "scale_y": 0.46692273468289613,
      "scale_z": 0.1999999999999993,
      "mode": "0"
    }
  },
  {
    "obj": {
      "type": "10",
      "start_x": 4.801197846482993,
      "start_y": -5.408495316809772,
      "start_z": 9.930197846482992,
      "scale_x": 0.20000000000000018,
      "scale_y": 0.11296517774586157,
      "scale_z": 0.1999999999999993,
      "mode": "0"
    }
  },
  {
    "obj": {
      "type": "11",
      "start_x": 4.801197846482993,
      "start_y": -5.1825649613180484,
      "start_z": 9.930197846482992,
      "scale_x": 0.10000000000000009,
      "scale_y": 0.11296517774586201,
      "scale_z": 0.09999999999999964,
      "mode": "0"
    }
  },
  {
    "obj": {
      "type": "4",
      "start_x": 5.739897846482993,
      "start_y": -6.51580215351701,
      "start_z": 9.930197846482992,
      "scale_x": 0.7386999999999997,
      "scale_y": 0.06000000000000005,
      "scale_z": 0.1999999999999993,
      "mode": "0"
    }
  },
  {
    "obj": {
      "type": "14",
      "start_x": 6.678597846482993,
      "start_y": -6.45580215351701,
      "start_z": 9.930197846482992,
      "scale_x": 0.20000000000000018,
      "scale_y": 0.1200000000000001,
      "scale_z": 0.1999999999999993,
      "mode": "0"
    }
  },
  {
    "obj": {
      "type": "14",
      "start_x": 6.678597846482993,
      "start_y": -6.45580215351701,
      "start_z": 9.930197846482992,
      "scale_x": 0.20000000000000018,
      "scale_y": 0.1200000000000001,
      "scale_z": 0.1999999999999993,
      "mode": "0"
    }
  },
  {
    "obj": {
      "type": "1",
      "start_x": 6.678597846482993,
      "start_y": -5.388802153517011,
      "start_z": 9.930197846482992,
      "scale_x": 0.1200000000000001,
      "scale_y": 0.5869999999999997,
      "scale_z": 0.07999999999999972,
      "mode": "0"
    }
  },
  {
    "obj": {
      "type": "13",
      "start_x": 6.678597846482993,
      "start_y": -4.741346863101662,
      "start_z": 9.930197846482992,
      "scale_x": 0.20000000000000018,
      "scale_y": 0.060455290415348806,
      "scale_z": 0.1999999999999993,
      "mode": "0"
    }
  },
  {
    "obj": {
      "type": "9",
      "start_x": 6.678597846482993,
      "start_y": -4.212363071967361,
      "start_z": 9.930197846482992,
      "scale_x": 0.20000000000000018,
      "scale_y": 0.4685285007189526,
      "scale_z": 0.1999999999999993,
      "mode": "0"
    }
  },
  {
    "obj": {
      "type": "10",
      "start_x": 6.678597846482993,
      "start_y": -3.6304809017196296,
      "start_z": 9.930197846482992,
      "scale_x": 0.20000000000000018,
      "scale_y": 0.11335366952877868,
      "scale_z": 0.1999999999999993,
      "mode": "0"
    }
  },
  {
    "obj": {
      "type": "11",
      "start_x": 6.678597846482993,
      "start_y": -3.4037735626620718,
      "start_z": 9.930197846482992,
      "scale_x": 0.10000000000000009,
      "scale_y": 0.1133536695287789,
      "scale_z": 0.09999999999999964,
      "mode": "0"
    }
  },
  {
    "obj": {
      "type": "4",
      "start_x": 7.472997846482993,
      "start_y": -4.7418021535170105,
      "start_z": 9.930197846482992,
      "scale_x": 0.5944000000000003,
      "scale_y": 0.06000000000000005,
      "scale_z": 0.1999999999999993,
      "mode": "0"
    }
  },
  {
    "obj": {
      "type": "13",
      "start_x": 8.267397846482993,
      "start_y": -4.74881249120911,
      "start_z": 9.930197846482992,
      "scale_x": 0.1999999999999993,
      "scale_y": 0.0529896623079007,
      "scale_z": 0.1999999999999993,
      "mode": "0"
    }
  },
  {
    "obj": {
      "type": "9",
      "start_x": 8.267397846482993,
      "start_y": -4.28515294601498,
      "start_z": 9.930197846482992,
      "scale_x": 0.1999999999999993,
      "scale_y": 0.4106698828862294,
      "scale_z": 0.1999999999999993,
      "mode": "0"
    }
  },
  {
    "obj": {
      "type": "10",
      "start_x": 8.267397846482993,
      "start_y": -3.7751274463014375,
      "start_z": 9.930197846482992,
      "scale_x": 0.1999999999999993,
      "scale_y": 0.09935561682731331,
      "scale_z": 0.1999999999999993,
      "mode": "0"
    }
  },
  {
    "obj": {
      "type": "11",
      "start_x": 8.267397846482993,
      "start_y": -3.5764162126468104,
      "start_z": 9.930197846482992,
      "scale_x": 0.09999999999999964,
      "scale_y": 0.09935561682731375,
      "scale_z": 0.09999999999999964,
      "mode": "0"
    }
  },
  {
    "obj": {
      "type": "4",
      "start_x": 9.176797846482993,
      "start_y": -4.7418021535170105,
      "start_z": 9.930197846482992,
      "scale_x": 0.7094000000000005,
      "scale_y": 0.06000000000000005,
      "scale_z": 0.1999999999999993,
      "mode": "0"
    }
  },
  {
    "obj": {
      "type": "13",
      "start_x": 10.086197846482992,
      "start_y": -4.745992397936668,
      "start_z": 9.930197846482992,
      "scale_x": 0.1999999999999993,
      "scale_y": 0.055809755580342735,
      "scale_z": 0.1999999999999993,
      "mode": "0"
    }
  },
  {
    "obj": {
      "type": "9",
      "start_x": 10.086197846482992,
      "start_y": -4.25765703660867,
      "start_z": 9.930197846482992,
      "scale_x": 0.1999999999999993,
      "scale_y": 0.4325256057476552,
      "scale_z": 0.1999999999999993,
      "mode": "0"
    }
  },
  {
    "obj": {
      "type": "10",
      "start_x": 10.086197846482992,
      "start_y": -3.720488139147873,
      "start_z": 9.930197846482992,
      "scale_x": 0.1999999999999993,
      "scale_y": 0.10464329171314235,
      "scale_z": 0.1999999999999993,
      "mode": "0"
    }
  },
  {
    "obj": {
      "type": "11",
      "start_x": 10.086197846482992,
      "start_y": -3.511201555721588,
      "start_z": 9.930197846482992,
      "scale_x": 0.09999999999999964,
      "scale_y": 0.10464329171314235,
      "scale_z": 0.09999999999999964,
      "mode": "0"
    }
  },
  {
    "obj": {
      "type": "12",
      "start_x": 10.086197846482992,
      "start_y": -4.7418021535170105,
      "start_z": 9.300597846482992,
      "scale_x": 0.1999999999999993,
      "scale_y": 0.06000000000000005,
      "scale_z": 0.42960000000000065,
      "mode": "0"
    }
  },
  {
    "obj": {
      "type": "13",
      "start_x": 10.086197846482992,
      "start_y": -4.747027534370309,
      "start_z": 8.670997846482992,
      "scale_x": 0.1999999999999993,
      "scale_y": 0.05477461914670245,
      "scale_z": 0.1999999999999993,
      "mode": "0"
    }
  },
  {
    "obj": {
      "type": "9",
      "start_x": 10.086197846482992,
      "start_y": -4.267749616836664,
      "start_z": 8.670997846482992,
      "scale_x": 0.1999999999999993,
      "scale_y": 0.4245032983869428,
      "scale_z": 0.1999999999999993,
      "mode": "0"
    }
  },
  {
    "obj": {
      "type": "10",
      "start_x": 10.086197846482992,
      "start_y": -3.740543907549654,
      "start_z": 8.670997846482992,
      "scale_x": 0.1999999999999993,
      "scale_y": 0.10270241090006671,
      "scale_z": 0.1999999999999993,
      "mode": "0"
    }
  },
  {
    "obj": {
      "type": "11",
      "start_x": 10.086197846482992,
      "start_y": -3.5351390857495204,
      "start_z": 8.670997846482992,
      "scale_x": 0.09999999999999964,
      "scale_y": 0.10270241090006693,
      "scale_z": 0.09999999999999964,
      "mode": "0"
    }
  },
  {
    "obj": {
      "type": "1",
      "start_x": 10.086197846482992,
      "start_y": -5.368802153517011,
      "start_z": 8.670997846482992,
      "scale_x": 0.11999999999999957,
      "scale_y": 0.5670000000000002,
      "scale_z": 0.07999999999999972,
      "mode": "0"
    }
  },
  {
    "obj": {
      "type": "14",
      "start_x": 10.086197846482992,
      "start_y": -6.415802153517011,
      "start_z": 8.670997846482992,
      "scale_x": 0.1999999999999993,
      "scale_y": 0.1200000000000001,
      "scale_z": 0.1999999999999993,
      "mode": "0"
    }
  },
  {
    "obj": {
      "type": "14",
      "start_x": 10.086197846482992,
      "start_y": -6.415802153517011,
      "start_z": 8.670997846482992,
      "scale_x": 0.1999999999999993,
      "scale_y": 0.1200000000000001,
      "scale_z": 0.1999999999999993,
      "mode": "0"
    }
  },
  {
    "obj": {
      "type": "12",
      "start_x": 10.086197846482992,
      "start_y": -6.4758021535170105,
      "start_z": 9.556297846482991,
      "scale_x": 0.1999999999999993,
      "scale_y": 0.06000000000000005,
      "scale_z": 0.6852999999999998,
      "mode": "0"
    }
  },
  {
    "obj": {
      "type": "13",
      "start_x": 10.086197846482992,
      "start_y": -6.475518903529187,
      "start_z": 10.44159784648299,
      "scale_x": 0.1999999999999993,
      "scale_y": 0.060283249987824306,
      "scale_z": 0.1999999999999993,
      "mode": "0"
    }
  },
  {
    "obj": {
      "type": "9",
      "start_x": 10.086197846482992,
      "start_y": -5.948040466135725,
      "start_z": 10.44159784648299,
      "scale_x": 0.1999999999999993,
      "scale_y": 0.46719518740563704,
      "scale_z": 0.1999999999999993,
      "mode": "0"
    }
  },
  {
    "obj": {
      "type": "10",
      "start_x": 10.086197846482992,
      "start_y": -5.367814185002918,
      "start_z": 10.44159784648299,
      "scale_x": 0.1999999999999993,
      "scale_y": 0.11303109372717035,
      "scale_z": 0.1999999999999993,
      "mode": "0"
    }
  },
  {
    "obj": {
      "type": "11",
      "start_x": 10.086197846482992,
      "start_y": -5.141751997548577,
      "start_z": 10.44159784648299,
      "scale_x": 0.09999999999999964,
      "scale_y": 0.11303109372717035,
      "scale_z": 0.09999999999999964,
      "mode": "0"
    }
  },
  {
    "obj": {
      "type": "4",
      "start_x": 10.895297846482991,
      "start_y": -6.4758021535170105,
      "start_z": 10.44159784648299,
      "scale_x": 0.6090999999999998,
      "scale_y": 0.06000000000000005,
      "scale_z": 0.1999999999999993,
      "mode": "0"
    }
  },
  {
    "obj": {
      "type": "14",
      "start_x": 11.70439784648299,
      "start_y": -6.415802153517011,
      "start_z": 10.44159784648299,
      "scale_x": 0.1999999999999993,
      "scale_y": 0.1200000000000001,
      "scale_z": 0.1999999999999993,
      "mode": "0"
    }
  },
  {
    "obj": {
      "type": "14",
      "start_x": 11.70439784648299,
      "start_y": -6.415802153517011,
      "start_z": 10.44159784648299,
      "scale_x": 0.1999999999999993,
      "scale_y": 0.1200000000000001,
      "scale_z": 0.1999999999999993,
      "mode": "0"
    }
  },
  {
    "obj": {
      "type": "1",
      "start_x": 11.70439784648299,
      "start_y": -5.495102153517012,
      "start_z": 10.44159784648299,
      "scale_x": 0.11999999999999957,
      "scale_y": 0.44069999999999965,
      "scale_z": 0.07999999999999972,
      "mode": "0"
    }
  },
  {
    "obj": {
      "type": "14",
      "start_x": 11.70439784648299,
      "start_y": -4.934402153517012,
      "start_z": 10.44159784648299,
      "scale_x": 0.1999999999999993,
      "scale_y": 0.1200000000000001,
      "scale_z": 0.1999999999999993,
      "mode": "0"
    }
  },
  {
    "obj": {
      "type": "14",
      "start_x": 11.70439784648299,
      "start_y": -4.934402153517012,
      "start_z": 10.44159784648299,
      "scale_x": 0.1999999999999993,
      "scale_y": 0.1200000000000001,
      "scale_z": 0.1999999999999993,
      "mode": "0"
    }
  },
  {
    "obj": {
      "type": "1",
      "start_x": 11.70439784648299,
      "start_y": -3.914102153517012,
      "start_z": 10.44159784648299,
      "scale_x": 0.11999999999999957,
      "scale_y": 0.5403000000000002,
      "scale_z": 0.07999999999999972,
      "mode": "0"
    }
  },
  {
    "obj": {
      "type": "13",
      "start_x": 11.70439784648299,
      "start_y": -3.3244516771249373,
      "start_z": 10.44159784648299,
      "scale_x": 0.1999999999999993,
      "scale_y": 0.04935047639207468,
      "scale_z": 0.1999999999999993,
      "mode": "0"
    }
  },
  {
    "obj": {
      "type": "9",
      "start_x": 11.70439784648299,
      "start_y": -2.8926350086942847,
      "start_z": 10.44159784648299,
      "scale_x": 0.1999999999999993,
      "scale_y": 0.3824661920385779,
      "scale_z": 0.1999999999999993,
      "mode": "0"
    }
  },
  {
    "obj": {
      "type": "10",
      "start_x": 11.70439784648299,
      "start_y": -2.417636673420567,
      "start_z": 10.44159784648299,
      "scale_x": 0.1999999999999993,
      "scale_y": 0.09253214323513981,
      "scale_z": 0.1999999999999993,
      "mode": "0"
    }
  },
  {
    "obj": {
      "type": "11",
      "start_x": 11.70439784648299,
      "start_y": -2.232572386950287,
      "start_z": 10.44159784648299,
      "scale_x": 0.09999999999999964,
      "scale_y": 0.09253214323513981,
      "scale_z": 0.09999999999999964,
      "mode": "0"
    }
  },
  {
    "obj": {
      "type": "4",
      "start_x": 12.37669784648299,
      "start_y": -3.313802153517012,
      "start_z": 10.44159784648299,
      "scale_x": 0.4723000000000006,
      "scale_y": 0.06000000000000005,
      "scale_z": 0.1999999999999993,
      "mode": "0"
    }
  },
  {
    "obj": {
      "type": "13",
      "start_x": 13.04899784648299,
      "start_y": -3.3147854793454745,
      "start_z": 10.44159784648299,
      "scale_x": 0.1999999999999993,
      "scale_y": 0.05901667417153744,
      "scale_z": 0.1999999999999993,
      "mode": "0"
    }
  },
  {
    "obj": {
      "type": "9",
      "start_x": 13.04899784648299,
      "start_y": -2.7983895803445225,
      "start_z": 10.44159784648299,
      "scale_x": 0.1999999999999993,
      "scale_y": 0.4573792248294146,
      "scale_z": 0.1999999999999993,
      "mode": "0"
    }
  },
  {
    "obj": {
      "type": "10",
      "start_x": 13.04899784648299,
      "start_y": -2.230354091443475,
      "start_z": 10.44159784648299,
      "scale_x": 0.1999999999999993,
      "scale_y": 0.11065626407163265,
      "scale_z": 0.1999999999999993,
      "mode": "0"
    }
  },
  {
    "obj": {
      "type": "11",
      "start_x": 13.04899784648299,
      "start_y": -2.00904156330021,
      "start_z": 10.44159784648299,
      "scale_x": 0.09999999999999964,
      "scale_y": 0.11065626407163265,
      "scale_z": 0.09999999999999964,
      "mode": "0"
    }
  },
  {
    "obj": {
      "type": "1",
      "start_x": 13.04899784648299,
      "start_y": -3.878702153517012,
      "start_z": 10.44159784648299,
      "scale_x": 0.11999999999999957,
      "scale_y": 0.5049000000000001,
      "scale_z": 0.07999999999999972,
      "mode": "0"
    }
  },
  {
    "obj": {
      "type": "14",
      "start_x": 13.04899784648299,
      "start_y": -4.863602153517012,
      "start_z": 10.44159784648299,
      "scale_x": 0.1999999999999993,
      "scale_y": 0.1200000000000001,
      "scale_z": 0.1999999999999993,
      "mode": "0"
    }
  },
  {
    "obj": {
      "type": "14",
      "start_x": 13.04899784648299,
      "start_y": -4.863602153517012,
      "start_z": 10.44159784648299,
      "scale_x": 0.1999999999999993,
      "scale_y": 0.1200000000000001,
      "scale_z": 0.1999999999999993,
      "mode": "0"
    }
  },
  {
    "obj": {
      "type": "12",
      "start_x": 13.04899784648299,
      "start_y": -4.923602153517011,
      "start_z": 11.40079784648299,
      "scale_x": 0.1999999999999993,
      "scale_y": 0.06000000000000005,
      "scale_z": 0.7591999999999999,
      "mode": "0"
    }
  },
  {
    "obj": {
      "type": "14",
      "start_x": 13.04899784648299,
      "start_y": -4.863602153517012,
      "start_z": 12.359997846482988,
      "scale_x": 0.1999999999999993,
      "scale_y": 0.1200000000000001,
      "scale_z": 0.1999999999999993,
      "mode": "0"
    }
  },
  {
    "obj": {
      "type": "14",
      "start_x": 13.04899784648299,
      "start_y": -4.863602153517012,
      "start_z": 12.359997846482988,
      "scale_x": 0.1999999999999993,
      "scale_y": 0.1200000000000001,
      "scale_z": 0.1999999999999993,
      "mode": "0"
    }
  },
  {
    "obj": {
      "type": "1",
      "start_x": 13.04899784648299,
      "start_y": -3.939302153517012,
      "start_z": 12.359997846482988,
      "scale_x": 0.11999999999999957,
      "scale_y": 0.44430000000000014,
      "scale_z": 0.07999999999999972,
      "mode": "0"
    }
  },
  {
    "obj": {
      "type": "13",
      "start_x": 13.04899784648299,
      "start_y": -3.4367368544870933,
      "start_z": 12.359997846482988,
      "scale_x": 0.1999999999999993,
      "scale_y": 0.05826529902991884,
      "scale_z": 0.1999999999999993,
      "mode": "0"
    }
  },
  {
    "obj": {
      "type": "9",
      "start_x": 13.04899784648299,
      "start_y": -2.926915487975304,
      "start_z": 12.359997846482988,
      "scale_x": 0.1999999999999993,
      "scale_y": 0.4515560674818706,
      "scale_z": 0.1999999999999993,
      "mode": "0"
    }
  },
  {
    "obj": {
      "type": "10",
      "start_x": 13.04899784648299,
      "start_y": -2.3661119848123353,
      "start_z": 12.359997846482988,
      "scale_x": 0.1999999999999993,
      "scale_y": 0.10924743568109774,
      "scale_z": 0.1999999999999993,
      "mode": "0"
    }
  },
  {
    "obj": {
      "type": "11",
      "start_x": 13.04899784648299,
      "start_y": -2.14761711345014,
      "start_z": 12.359997846482988,
      "scale_x": 0.09999999999999964,
      "scale_y": 0.10924743568109774,
      "scale_z": 0.09999999999999964,
      "mode": "0"
    }
  },
  {
    "obj": {
      "type": "4",
      "start_x": 13.71299784648299,
      "start_y": -3.435002153517012,
      "start_z": 12.359997846482988,
      "scale_x": 0.4640000000000004,
      "scale_y": 0.06000000000000005,
      "scale_z": 0.1999999999999993,
      "mode": "0"
    }
  },
  {
    "obj": {
      "type": "13",
      "start_x": 14.37699784648299,
      "start_y": -3.434890078629534,
      "start_z": 12.359997846482988,
      "scale_x": 0.1999999999999993,
      "scale_y": 0.06011207488747794,
      "scale_z": 0.1999999999999993,
      "mode": "0"
    }
  },
  {
    "obj": {
      "type": "9",
      "start_x": 14.37699784648299,
      "start_y": -2.9089094233641024,
      "start_z": 12.359997846482988,
      "scale_x": 0.1999999999999993,
      "scale_y": 0.4658685803779541,
      "scale_z": 0.1999999999999993,
      "mode": "0"
    }
  },
  {
    "obj": {
      "type": "10",
      "start_x": 14.37699784648299,
      "start_y": -2.3303307025721267,
      "start_z": 12.359997846482988,
      "scale_x": 0.1999999999999993,
      "scale_y": 0.11271014041402139,
      "scale_z": 0.1999999999999993,
      "mode": "0"
    }
  },
  {
    "obj": {
      "type": "11",
      "start_x": 14.37699784648299,
      "start_y": -2.1049104217440844,
      "start_z": 12.359997846482988,
      "scale_x": 0.09999999999999964,
      "scale_y": 0.11271014041402116,
      "scale_z": 0.09999999999999964,
      "mode": "0"
    }
  },
  {
    "obj": {
      "type": "13",
      "start_x": 0.8629989232414947,
      "start_y": 5.25409115808208,
      "start_z": 5.918398923241496,
      "scale_x": 0.19999999999999996,
      "scale_y": 0.05189223484058525,
      "scale_z": 0.20000000000000018,
      "mode": "0"
    }
  },
  {
    "obj": {
      "type": "9",
      "start_x": 0.8629989232414947,
      "start_y": 5.7081482129372,
      "start_z": 5.918398923241496,
      "scale_x": 0.19999999999999996,
      "scale_y": 0.402164820014534,
      "scale_z": 0.20000000000000018,
      "mode": "0"
    }
  },
  {
    "obj": {
      "type": "10",
      "start_x": 0.8629989232414947,
      "start_y": 6.207610973277831,
      "start_z": 5.918398923241496,
      "scale_x": 0.19999999999999996,
      "scale_y": 0.09729794032609718,
      "scale_z": 0.20000000000000018,
      "mode": "0"
    }
  },
  {
    "obj": {
      "type": "11",
      "start_x": 0.8629989232414947,
      "start_y": 6.402206853930025,
      "start_z": 5.918398923241496,
      "scale_x": 0.09999999999999998,
      "scale_y": 0.09729794032609718,
      "scale_z": 0.10000000000000009,
      "mode": "0"
    }
  },
  {
    "obj": {
      "type": "4",
      "start_x": 1.8629989232414947,
      "start_y": 5.262198923241495,
      "start_z": 5.918398923241496,
      "scale_x": 0.8,
      "scale_y": 0.06000000000000005,
      "scale_z": 0.20000000000000018,
      "mode": "0"
    }
  },
  {
    "obj": {
      "type": "13",
      "start_x": 2.862998923241495,
      "start_y": 5.261706991022817,
      "start_z": 5.918398923241496,
      "scale_x": 0.20000000000000018,
      "scale_y": 0.059508067781322005,
      "scale_z": 0.20000000000000018,
      "mode": "0"
    }
  },
  {
    "obj": {
      "type": "9",
      "start_x": 2.862998923241495,
      "start_y": 5.782402584109385,
      "start_z": 5.918398923241496,
      "scale_x": 0.20000000000000018,
      "scale_y": 0.4611875253052462,
      "scale_z": 0.20000000000000018,
      "mode": "0"
    }
  },
  {
    "obj": {
      "type": "10",
      "start_x": 2.862998923241495,
      "start_y": 6.35516773650461,
      "start_z": 5.918398923241496,
      "scale_x": 0.20000000000000018,
      "scale_y": 0.11157762708997909,
      "scale_z": 0.20000000000000018,
      "mode": "0"
    }
  },
  {
    "obj": {
      "type": "11",
      "start_x": 2.862998923241495,
      "start_y": 6.578322990684569,
      "start_z": 5.918398923241496,
      "scale_x": 0.10000000000000009,
      "scale_y": 0.11157762708997909,
      "scale_z": 0.10000000000000009,
      "mode": "0"
    }
  },
  {
    "obj": {
      "type": "4",
      "start_x": 3.862998923241495,
      "start_y": 5.262198923241495,
      "start_z": 5.918398923241496,
      "scale_x": 0.7999999999999998,
      "scale_y": 0.06000000000000005,
      "scale_z": 0.20000000000000018,
      "mode": "0"
    }
  },
  {
    "obj": {
      "type": "13",
      "start_x": 4.862998923241495,
      "start_y": 5.252209570310459,
      "start_z": 5.918398923241496,
      "scale_x": 0.20000000000000018,
      "scale_y": 0.050010647068964076,
      "scale_z": 0.20000000000000018,
      "mode": "0"
    }
  },
  {
    "obj": {
      "type": "9",
      "start_x": 4.862998923241495,
      "start_y": 5.689802732163894,
      "start_z": 5.918398923241496,
      "scale_x": 0.20000000000000018,
      "scale_y": 0.38758251478447114,
      "scale_z": 0.20000000000000018,
      "mode": "0"
    }
  },
  {
    "obj": {
      "type": "10",
      "start_x": 4.862998923241495,
      "start_y": 6.171155210202673,
      "start_z": 5.918398923241496,
      "scale_x": 0.20000000000000018,
      "scale_y": 0.09376996325430742,
      "scale_z": 0.20000000000000018,
      "mode": "0"
    }
  },
  {
    "obj": {
      "type": "11",
      "start_x": 4.862998923241495,
      "start_y": 6.358695136711288,
      "start_z": 5.918398923241496,
      "scale_x": 0.10000000000000009,
      "scale_y": 0.09376996325430742,
      "scale_z": 0.10000000000000009,
      "mode": "0"
    }
  },
  {
    "obj": {
      "type": "4",
      "start_x": 5.862998923241495,
      "start_y": 5.262198923241495,
      "start_z": 5.918398923241496,
      "scale_x": 0.7999999999999998,
      "scale_y": 0.06000000000000005,
      "scale_z": 0.20000000000000018,
      "mode": "0"
    }
  },
  {
    "obj": {
      "type": "13",
      "start_x": 6.862998923241495,
      "start_y": 5.254101954789578,
      "start_z": 5.918398923241496,
      "scale_x": 0.20000000000000018,
      "scale_y": 0.05190303154808351,
      "scale_z": 0.20000000000000018,
      "mode": "0"
    }
  },
  {
    "obj": {
      "type": "9",
      "start_x": 6.862998923241495,
      "start_y": 5.70825348083531,
      "start_z": 5.918398923241496,
      "scale_x": 0.20000000000000018,
      "scale_y": 0.4022484944976483,
      "scale_z": 0.20000000000000018,
      "mode": "0"
    }
  },
  {
    "obj": {
      "type": "10",
      "start_x": 6.862998923241495,
      "start_y": 6.207820159485616,
      "start_z": 5.918398923241496,
      "scale_x": 0.20000000000000018,
      "scale_y": 0.0973181841526567,
      "scale_z": 0.20000000000000018,
      "mode": "0"
    }
  },
  {
    "obj": {
      "type": "11",
      "start_x": 6.862998923241495,
      "start_y": 6.402456527790928,
      "start_z": 5.918398923241496,
      "scale_x": 0.10000000000000009,
      "scale_y": 0.0973181841526567,
      "scale_z": 0.10000000000000009,
      "mode": "0"
    }
  },
  {
    "obj": {
      "type": "4",
      "start_x": 7.862998923241495,
      "start_y": 5.262198923241495,
      "start_z": 5.918398923241496,
      "scale_x": 0.8000000000000003,
      "scale_y": 0.06000000000000005,
      "scale_z": 0.20000000000000018,
      "mode": "0"
    }
  },
  {
    "obj": {
      "type": "13",
      "start_x": 8.862998923241495,
      "start_y": 5.255926380766065,
      "start_z": 5.918398923241496,
      "scale_x": 0.1999999999999993,
      "scale_y": 0.05372745752457053,
      "scale_z": 0.20000000000000018,
      "mode": "0"
    }
  },
  {
    "obj": {
      "type": "9",
      "start_x": 8.862998923241495,
      "start_y": 5.726041634106057,
      "start_z": 5.918398923241496,
      "scale_x": 0.1999999999999993,
      "scale_y": 0.4163877958154214,
      "scale_z": 0.20000000000000018,
      "mode": "0"
    }
  },
  {
    "obj": {
      "type": "10",
      "start_x": 8.862998923241495,
      "start_y": 6.243168412780048,
      "start_z": 5.918398923241496,
      "scale_x": 0.1999999999999993,
      "scale_y": 0.10073898285856941,
      "scale_z": 0.20000000000000018,
      "mode": "0"
    }
  },
  {
    "obj": {
      "type": "11",
      "start_x": 8.862998923241495,
      "start_y": 6.444646378497188,
      "start_z": 5.918398923241496,
      "scale_x": 0.09999999999999964,
      "scale_y": 0.10073898285856986,
      "scale_z": 0.10000000000000009,
      "mode": "0"
    }
  },
  {
    "obj": {
      "type": "4",
      "start_x": 9.862998923241495,
      "start_y": 5.262198923241495,
      "start_z": 5.918398923241496,
      "scale_x": 0.8000000000000007,
      "scale_y": 0.06000000000000005,
      "scale_z": 0.20000000000000018,
      "mode": "0"
    }
  },
  {
    "obj": {
      "type": "13",
      "start_x": 10.862998923241495,
      "start_y": 5.25333066298437,
      "start_z": 5.918398923241496,
      "scale_x": 0.1999999999999993,
      "scale_y": 0.05113173974287477,
      "scale_z": 0.20000000000000018,
      "mode": "0"
    }
  },
  {
    "obj": {
      "type": "9",
      "start_x": 10.862998923241495,
      "start_y": 5.700733385734524,
      "start_z": 5.918398923241496,
      "scale_x": 0.1999999999999993,
      "scale_y": 0.3962709830072795,
      "scale_z": 0.20000000000000018,
      "mode": "0"
    }
  },
  {
    "obj": {
      "type": "10",
      "start_x": 10.862998923241495,
      "start_y": 6.192876380759694,
      "start_z": 5.918398923241496,
      "scale_x": 0.1999999999999993,
      "scale_y": 0.0958720120178902,
      "scale_z": 0.20000000000000018,
      "mode": "0"
    }
  },
  {
    "obj": {
      "type": "11",
      "start_x": 10.862998923241495,
      "start_y": 6.3846204047954735,
      "start_z": 5.918398923241496,
      "scale_x": 0.09999999999999964,
      "scale_y": 0.0958720120178902,
      "scale_z": 0.10000000000000009,
      "mode": "0"
    }
  },
  {
    "obj": {
      "type": "4",
      "start_x": 11.716198384862242,
      "start_y": 5.262198923241495,
      "start_z": 5.918398923241496,
      "scale_x": 0.6531994616207477,
      "scale_y": 0.06000000000000005,
      "scale_z": 0.20000000000000018,
      "mode": "0"
    }
  },
  {
    "obj": {
      "type": "13",
      "start_x": 12.569397846482989,
      "start_y": 5.2578086168781155,
      "start_z": 5.918398923241496,
      "scale_x": 0.1999999999999993,
      "scale_y": 0.055609693636620605,
      "scale_z": 0.20000000000000018,
      "mode": "0"
    }
  },
  {
    "obj": {
      "type": "9",
      "start_x": 12.569397846482989,
      "start_y": 5.744393436198545,
      "start_z": 5.918398923241496,
      "scale_x": 0.1999999999999993,
      "scale_y": 0.43097512568380925,
      "scale_z": 0.20000000000000018,
      "mode": "0"
    }
  },
  {
    "obj": {
      "type": "10",
      "start_x": 12.569397846482989,
      "start_y": 6.279636737451018,
      "start_z": 5.918398923241496,
      "scale_x": 0.1999999999999993,
      "scale_y": 0.10426817556866341,
      "scale_z": 0.20000000000000018,
      "mode": "0"
    }
  },
  {
    "obj": {
      "type": "11",
      "start_x": 12.569397846482989,
      "start_y": 6.488173088588345,
      "start_z": 5.918398923241496,
      "scale_x": 0.09999999999999964,
      "scale_y": 0.10426817556866341,
      "scale_z": 0.10000000000000009,
      "mode": "0"
    }
  },
  {
    "obj": {
      "type": "4",
      "start_x": 13.473197846482988,
      "start_y": 5.262198923241495,
      "start_z": 5.918398923241496,
      "scale_x": 0.7037999999999993,
      "scale_y": 0.06000000000000005,
      "scale_z": 0.20000000000000018,
      "mode": "0"
    }
  },
  {
    "obj": {
      "type": "13",
      "start_x": 14.376997846482986,
      "start_y": 5.259466204873238,
      "start_z": 5.918398923241496,
      "scale_x": 0.1999999999999993,
      "scale_y": 0.057267281631743217,
      "scale_z": 0.20000000000000018,
      "mode": "0"
    }
  },
  {
    "obj": {
      "type": "9",
      "start_x": 14.376997846482986,
      "start_y": 5.760554919150989,
      "start_z": 5.918398923241496,
      "scale_x": 0.1999999999999993,
      "scale_y": 0.44382143264600815,
      "scale_z": 0.20000000000000018,
      "mode": "0"
    }
  },
  {
    "obj": {
      "type": "10",
      "start_x": 14.376997846482986,
      "start_y": 6.311752504856516,
      "start_z": 5.918398923241496,
      "scale_x": 0.1999999999999993,
      "scale_y": 0.10737615305951786,
      "scale_z": 0.20000000000000018,
      "mode": "0"
    }
  },
  {
    "obj": {
      "type": "11",
      "start_x": 14.376997846482986,
      "start_y": 6.526504810975552,
      "start_z": 5.918398923241496,
      "scale_x": 0.09999999999999964,
      "scale_y": 0.10737615305951831,
      "scale_z": 0.10000000000000009,
      "mode": "0"
    }
  },
  {
    "obj": {
      "type": "9",
      "start_x": 14.376997846482986,
      "start_y": 4.402198923241495,
      "start_z": 5.918398923241496,
      "scale_x": 0.1999999999999993,
      "scale_y": 0.7999999999999998,
      "scale_z": 0.20000000000000018,
      "mode": "0"
    }
  },
  {
    "obj": {
      "type": "14",
      "start_x": 14.376997846482986,
      "start_y": 3.1221989232414957,
      "start_z": 5.918398923241496,
      "scale_x": 0.1999999999999993,
      "scale_y": 0.11999999999999988,
      "scale_z": 0.20000000000000018,
      "mode": "0"
    }
  },
  {
    "obj": {
      "type": "14",
      "start_x": 14.376997846482986,
      "start_y": 3.1221989232414957,
      "start_z": 5.918398923241496,
      "scale_x": 0.1999999999999993,
      "scale_y": 0.11999999999999988,
      "scale_z": 0.20000000000000018,
      "mode": "0"
    }
  },
  {
    "obj": {
      "type": "1",
      "start_x": 14.376997846482986,
      "start_y": 2.202198923241496,
      "start_z": 5.918398923241496,
      "scale_x": 0.11999999999999957,
      "scale_y": 0.7999999999999999,
      "scale_z": 0.08000000000000007,
      "mode": "0"
    }
  },
  {
    "obj": {
      "type": "14",
      "start_x": 14.376997846482986,
      "start_y": 0.9221989232414957,
      "start_z": 5.918398923241496,
      "scale_x": 0.1999999999999993,
      "scale_y": 0.12,
      "scale_z": 0.20000000000000018,
      "mode": "0"
    }
  },
  {
    "obj": {
      "type": "14",
      "start_x": 14.376997846482986,
      "start_y": 0.9221989232414957,
      "start_z": 5.918398923241496,
      "scale_x": 0.1999999999999993,
      "scale_y": 0.12,
      "scale_z": 0.20000000000000018,
      "mode": "0"
    }
  },
  {
    "obj": {
      "type": "9",
      "start_x": 14.376997846482986,
      "start_y": 0.0021989232414956206,
      "start_z": 5.918398923241496,
      "scale_x": 0.1999999999999993,
      "scale_y": 0.8,
      "scale_z": 0.20000000000000018,
      "mode": "0"
    }
  },
  {
    "obj": {
      "type": "14",
      "start_x": 14.376997846482986,
      "start_y": -1.2778010767585046,
      "start_z": 5.918398923241496,
      "scale_x": 0.1999999999999993,
      "scale_y": 0.12,
      "scale_z": 0.20000000000000018,
      "mode": "0"
    }
  },
  {
    "obj": {
      "type": "14",
      "start_x": 14.376997846482986,
      "start_y": -1.2778010767585046,
      "start_z": 5.918398923241496,
      "scale_x": 0.1999999999999993,
      "scale_y": 0.12,
      "scale_z": 0.20000000000000018,
      "mode": "0"
    }
  },
  {
    "obj": {
      "type": "1",
      "start_x": 14.376997846482986,
      "start_y": -2.146401615137758,
      "start_z": 5.918398923241496,
      "scale_x": 0.11999999999999957,
      "scale_y": 0.7486005383792534,
      "scale_z": 0.08000000000000007,
      "mode": "0"
    }
  },
  {
    "obj": {
      "type": "14",
      "start_x": 14.376997846482986,
      "start_y": -3.375002153517011,
      "start_z": 5.918398923241496,
      "scale_x": 0.1999999999999993,
      "scale_y": 0.11999999999999988,
      "scale_z": 0.20000000000000018,
      "mode": "0"
    }
  },
  {
    "obj": {
      "type": "14",
      "start_x": 14.376997846482986,
      "start_y": -3.375002153517011,
      "start_z": 5.918398923241496,
      "scale_x": 0.1999999999999993,
      "scale_y": 0.11999999999999988,
      "scale_z": 0.20000000000000018,
      "mode": "0"
    }
  },
  {
    "obj": {
      "type": "12",
      "start_x": 14.376997846482986,
      "start_y": -3.435002153517011,
      "start_z": 6.716898384862242,
      "scale_x": 0.1999999999999993,
      "scale_y": 0.06000000000000005,
      "scale_z": 0.5984994616207455,
      "mode": "0"
    }
  },
  {
    "obj": {
      "type": "13",
      "start_x": 14.376997846482986,
      "start_y": -3.441479484821703,
      "start_z": 7.515397846482988,
      "scale_x": 0.1999999999999993,
      "scale_y": 0.05352266869530786,
      "scale_z": 0.20000000000000018,
      "mode": "0"
    }
  },
  {
    "obj": {
      "type": "9",
      "start_x": 14.376997846482986,
      "start_y": -2.973156133737759,
      "start_z": 7.515397846482988,
      "scale_x": 0.1999999999999993,
      "scale_y": 0.4148006823886361,
      "scale_z": 0.20000000000000018,
      "mode": "0"
    }
  },
  {
    "obj": {
      "type": "10",
      "start_x": 14.376997846482986,
      "start_y": -2.458000447545421,
      "start_z": 7.515397846482988,
      "scale_x": 0.1999999999999993,
      "scale_y": 0.10035500380370221,
      "scale_z": 0.20000000000000018,
      "mode": "0"
    }
  },
  {
    "obj": {
      "type": "11",
      "start_x": 14.376997846482986,
      "start_y": -2.2572904399380165,
      "start_z": 7.515397846482988,
      "scale_x": 0.09999999999999964,
      "scale_y": 0.10035500380370221,
      "scale_z": 0.10000000000000009,
      "mode": "0"
    }
  },
  {
    "obj": {
      "type": "12",
      "start_x": 14.376997846482986,
      "start_y": -3.435002153517011,
      "start_z": 8.316897846482988,
      "scale_x": 0.1999999999999993,
      "scale_y": 0.06000000000000005,
      "scale_z": 0.6014999999999997,
      "mode": "0"
    }
  },
  {
    "obj": {
      "type": "13",
      "start_x": 14.376997846482986,
      "start_y": -3.4384874138566346,
      "start_z": 9.118397846482987,
      "scale_x": 0.1999999999999993,
      "scale_y": 0.056514739660376456,
      "scale_z": 0.1999999999999993,
      "mode": "0"
    }
  },
  {
    "obj": {
      "type": "9",
      "start_x": 14.376997846482986,
      "start_y": -2.9439834418283404,
      "start_z": 9.118397846482987,
      "scale_x": 0.1999999999999993,
      "scale_y": 0.43798923236791776,
      "scale_z": 0.1999999999999993,
      "mode": "0"
    }
  },
  {
    "obj": {
      "type": "10",
      "start_x": 14.376997846482986,
      "start_y": -2.4000290725972167,
      "start_z": 9.118397846482987,
      "scale_x": 0.1999999999999993,
      "scale_y": 0.10596513686320597,
      "scale_z": 0.1999999999999993,
      "mode": "0"
    }
  },
  {
    "obj": {
      "type": "11",
      "start_x": 14.376997846482986,
      "start_y": -2.1880987988708047,
      "start_z": 9.118397846482987,
      "scale_x": 0.09999999999999964,
      "scale_y": 0.10596513686320597,
      "scale_z": 0.09999999999999964,
      "mode": "0"
    }
  },
  {
    "obj": {
      "type": "12",
      "start_x": 14.376997846482986,
      "start_y": -3.435002153517011,
      "start_z": 9.976897846482986,
      "scale_x": 0.1999999999999993,
      "scale_y": 0.06000000000000005,
      "scale_z": 0.6585000000000001,
      "mode": "0"
    }
  },
  {
    "obj": {
      "type": "13",
      "start_x": 14.376997846482986,
      "start_y": -3.4316503764061026,
      "start_z": 10.835397846482985,
      "scale_x": 0.1999999999999993,
      "scale_y": 0.06335177711090845,
      "scale_z": 0.1999999999999993,
      "mode": "0"
    }
  },
  {
    "obj": {
      "type": "9",
      "start_x": 14.376997846482986,
      "start_y": -2.877322326685653,
      "start_z": 10.835397846482985,
      "scale_x": 0.1999999999999993,
      "scale_y": 0.49097627260954124,
      "scale_z": 0.1999999999999993,
      "mode": "0"
    }
  },
  {
    "obj": {
      "type": "10",
      "start_x": 14.376997846482986,
      "start_y": -2.267561471993158,
      "start_z": 10.835397846482985,
      "scale_x": 0.1999999999999993,
      "scale_y": 0.11878458208295362,
      "scale_z": 0.1999999999999993,
      "mode": "0"
    }
  },
  {
    "obj": {
      "type": "11",
      "start_x": 14.376997846482986,
      "start_y": -2.029992307827251,
      "start_z": 10.835397846482985,
      "scale_x": 0.09999999999999964,
      "scale_y": 0.1187845820829535,
      "scale_z": 0.09999999999999964,
      "mode": "0"
    }
  },
  {
    "obj": {
      "type": "12",
      "start_x": 14.376997846482986,
      "start_y": -3.435002153517011,
      "start_z": 11.597697846482985,
      "scale_x": 0.1999999999999993,
      "scale_y": 0.06000000000000005,
      "scale_z": 0.5623000000000005,
      "mode": "0"
    }
  }
]