[
  {
    "obj": {
      "type": "0",
      "start_x": 3.217949192431123,
      "start_y": 2.819549192431123,
      "start_z": 3.217949192431123,
      "scale_x": 0.05999999999999978,
      "scale_y": 0.5380799999999999,
      "scale_z": 0.05999999999999978,
      "rotation_x": 0.0,
      "rotation_y": 0.3,
      "rotation_z": -0.3,
      "mode": "1"
    }
  },
  {
    "obj": {
      "type": "1",
      "start_x": 3.2156013862491144,
      "start_y": 2.3511553389873767,
      "start_z": 3.217949192431123,
      "scale_x": 0.00020000000000000017,
      "scale_y": 0.00020000000000000017,
      "scale_z": 0.00020000000000000017,
      "rotation_x": 0.0,
      "rotation_y": 0.3,
      "rotation_z": -0.3,
      "mode": "1"
    }
  },
  {
    "obj": {
      "type": "0",
      "start_x": 2.900701934555459,
      "start_y": 2.351260056828539,
      "start_z": 3.2180539117077513,
      "scale_x": 0.3538800000000002,
      "scale_y": 0.05999999999999978,
      "scale_z": 0.05999999999999978,
      "rotation_x": 0.0,
      "rotation_y": -0.4,
      "rotation_z": 0.3,
      "mode": "1"
    }
  },
  {
    "obj": {
      "type": "1",
      "start_x": 2.585813163378161,
      "start_y": 2.3497160087229334,
      "start_z": 3.2159951380458827,
      "scale_x": 0.00020000000000000017,
      "scale_y": 0.00020000000000000017,
      "scale_z": 0.00020000000000000017,
      "rotation_x": 0.0,
      "rotation_y": -0.4,
      "rotation_z": 0.3,
      "mode": "1"
    }
  },
  {
    "obj": {
      "type": "0",
      "start_x": 1.3700983848622457,
      "start_y": 1.4858983848622456,
      "start_z": 1.4858983848622456,
      "scale_x": 0.19895999999999994,
      "scale_y": 0.06000000000000005,
      "scale_z": 0.06000000000000005,
      "rotation_x": 0.0,
      "rotation_y": -0.4,
      "rotation_z": 0.3,
      "mode": "1"
    }
  },
  {
    "obj": {
      "type": "1",
      "start_x": 1.1843046979812828,
      "start_y": 1.4850302832145366,
      "start_z": 1.4847408919048435,
      "scale_x": 0.00020000000000000017,
      "scale_y": 0.00020000000000000017,
      "scale_z": 0.00020000000000000017,
      "rotation_x": 0.0,
      "rotation_y": -0.4,
      "rotation_z": 0.3,
      "mode": "1"
    }
  },
  {
    "obj": {
      "type": "0",
      "start_x": 1.1841650746892713,
      "start_y": 1.4850295521420083,
      "start_z": 1.7296404045189515,
      "scale_x": 0.06000000000000005,
      "scale_y": 0.06000000000000005,
      "scale_z": 0.26987999999999984,
      "rotation_x": 0.0,
      "rotation_y": 0.3,
      "rotation_z": -0.4,
      "mode": "1"
    }
  },
  {
    "obj": {
      "type": "1",
      "start_x": 1.1853426142584496,
      "start_y": 1.4850213312314269,
      "start_z": 1.9745373216453976,
      "scale_x": 0.00020000000000000017,
      "scale_y": 0.00020000000000000017,
      "scale_z": 0.00020000000000000017,
      "rotation_x": 0.0,
      "rotation_y": 0.3,
      "rotation_z": -0.4,
      "mode": "1"
    }
  },
  {
    "obj": {
      "type": "1",
      "start_x": 2.585813163378161,
      "start_y": 2.3497160087229334,
      "start_z": 3.2159951380458827,
      "scale_x": 0.00020000000000000017,
      "scale_y": 0.00020000000000000017,
      "scale_z": 0.00020000000000000017,
      "rotation_x": 0.0,
      "rotation_y": -0.4,
      "rotation_z": 0.3,
      "mode": "1"
    }
  },
  {
    "obj": {
      "type": "0",
      "start_x": 2.265813924912424,
      "start_y": 2.3496112919982397,
      "start_z": 3.2158555128399233,
      "scale_x": 0.35999999999999993,
      "scale_y": 0.05999999999999978,
      "scale_z": 0.05999999999999978,
      "rotation_x": 0.0,
      "rotation_y": 0.4,
      "rotation_z": -0.3,
      "mode": "1"
    }
  },
  {
    "obj": {
      "type": "1",
      "start_x": 1.945825347926363,
      "start_y": 2.351182042868642,
      "start_z": 3.2179498909293116,
      "scale_x": 0.00020000000000000017,
      "scale_y": 0.00020000000000000017,
      "scale_z": 0.00020000000000000017,
      "rotation_x": 0.0,
      "rotation_y": 0.4,
      "rotation_z": -0.3,
      "mode": "1"
    }
  },
  {
    "obj": {
      "type": "0",
      "start_x": 1.7254908349007698,
      "start_y": 2.3512867595933358,
      "start_z": 3.218089516135271,
      "scale_x": 0.24040232947182705,
      "scale_y": 0.05999999999999978,
      "scale_z": 0.05999999999999978,
      "rotation_x": 0.0,
      "rotation_y": -0.4,
      "rotation_z": 0.3,
      "mode": "1"
    }
  },
  {
    "obj": {
      "type": "1",
      "start_x": 1.5051631884496932,
      "start_y": 2.350237836903712,
      "start_z": 3.216690923436705,
      "scale_x": 0.00020000000000000017,
      "scale_y": 0.00020000000000000017,
      "scale_z": 0.00020000000000000017,
      "rotation_x": 0.0,
      "rotation_y": -0.4,
      "rotation_z": 0.3,
      "mode": "1"
    }
  },
  {
    "obj": {
      "type": "0",
      "start_x": 1.3452639499839558,
      "start_y": 2.3501331201790183,
      "start_z": 3.216551298230746,
      "scale_x": 0.1678799999999999,
      "scale_y": 0.05999999999999978,
      "scale_z": 0.05999999999999978,
      "rotation_x": 0.0,
      "rotation_y": 0.3,
      "rotation_z": -0.4,
      "mode": "1"
    }
  },
  {
    "obj": {
      "type": "1",
      "start_x": 1.1853692769161228,
      "start_y": 2.3511097851066385,
      "start_z": 3.217283809570761,
      "scale_x": 0.00020000000000000017,
      "scale_y": 0.00020000000000000017,
      "scale_z": 0.00020000000000000017,
      "rotation_x": 0.0,
      "rotation_y": 0.3,
      "rotation_z": -0.4,
      "mode": "1"
    }
  },
  {
    "obj": {
      "type": "0",
      "start_x": 1.1852296517101635,
      "start_y": 1.9187629337467773,
      "start_z": 3.217283809570761,
      "scale_x": 0.06000000000000005,
      "scale_y": 0.4948168064949039,
      "scale_z": 0.05999999999999978,
      "rotation_x": 0.0,
      "rotation_y": -0.3,
      "rotation_z": 0.4,
      "mode": "1"
    }
  },
  {
    "obj": {
      "type": "1",
      "start_x": 1.1881083558151193,
      "start_y": 1.4864256436148016,
      "start_z": 3.217283809570761,
      "scale_x": 0.00020000000000000017,
      "scale_y": 0.00020000000000000017,
      "scale_z": 0.00020000000000000017,
      "rotation_x": 0.0,
      "rotation_y": -0.3,
      "rotation_z": 0.4,
      "mode": "1"
    }
  },
  {
    "obj": {
      "type": "0",
      "start_x": 1.1882130725398128,
      "start_y": 1.4864263746873299,
      "start_z": 2.9009551755255703,
      "scale_x": 0.06000000000000005,
      "scale_y": 0.06000000000000005,
      "scale_z": 0.35559468984029097,
      "rotation_x": 0.0,
      "rotation_y": 0.3,
      "rotation_z": -0.3,
      "mode": "1"
    }
  },
  {
    "obj": {
      "type": "1",
      "start_x": 1.1866615263627749,
      "start_y": 1.4864344986383566,
      "start_z": 2.584630329328682,
      "scale_x": 0.00020000000000000017,
      "scale_y": 0.00020000000000000017,
      "scale_z": 0.00020000000000000017,
      "rotation_x": 0.0,
      "rotation_y": 0.3,
      "rotation_z": -0.3,
      "mode": "1"
    }
  },
  {
    "obj": {
      "type": "0",
      "start_x": 1.1865568085216125,
      "start_y": 1.4864350469447014,
      "start_z": 2.2802306034837336,
      "scale_x": 0.06000000000000005,
      "scale_y": 0.06000000000000005,
      "scale_z": 0.34127999999999986,
      "rotation_x": 0.0,
      "rotation_y": -0.4,
      "rotation_z": 0.4,
      "mode": "1"
    }
  },
  {
    "obj": {
      "type": "0",
      "start_x": 2.201057133560197,
      "start_y": 0.13502955214200818,
      "start_z": 2.351993950498758,
      "scale_x": 0.1200000000000001,
      "scale_y": 1.44,
      "scale_z": 0.1200000000000001,
      "rotation_x": 0.0,
      "rotation_y": 0.0,
      "rotation_z": 0.0,
      "mode": "1"
    }
  },
  {
    "obj": {
      "type": "0",
      "start_x": 5.267949192431123,
      "start_y": 5.267949192431123,
      "start_z": 0.4358983848622455,
      "scale_x": 0.2400000000000002,
      "scale_y": 0.2400000000000002,
      "scale_z": 0.23999999999999996,
      "rotation_x": 0.0,
      "rotation_y": 0.0,
      "rotation_z": 0.0,
      "mode": "1"
    }
  },
  {
    "obj": {
      "type": "0",
      "start_x": 0.0,
      "start_y": 0.0,
      "start_z": 0.0,
      "scale_x": 0.24,
      "scale_y": 0.036,
      "scale_z": 0.036,
      "rotation_x": 0.0,
      "rotation_y": 0.0,
      "rotation_z": 0.0,
      "mode": "1"
    }
  },
  {
    "obj": {
      "type": "0",
      "start_x": 0.0,
      "start_y": 0.0,
      "start_z": 0.0,
      "scale_x": 0.24,
      "scale_y": 0.036,
      "scale_z": 0.036,
      "rotation_x": 0.0,
      "rotation_y": 0.0,
      "rotation_z": 0.0,
      "mode": "1"
    }
  },
  {
    "obj": {
      "type": "0",
      "start_x": 0.15000000000000002,
      "start_y": 0.054,
      "start_z": 0.0,
      "scale_x": 0.19200000000000003,
      "scale_y": 0.0288,
      "scale_z": 0.0288,
      "rotation_x": 0.0,
      "rotation_y": 0.0,
      "rotation_z": 0.3,
      "mode": "1"
    }
  },
  {
    "obj": {
      "type": "0",
      "start_x": 0.15000000000000002,
      "start_y": -0.054,
      "start_z": 0.0,
      "scale_x": 0.19200000000000003,
      "scale_y": 0.0288,
      "scale_z": 0.0288,
      "rotation_x": 0.0,
      "rotation_y": 0.0,
      "rotation_z": -0.3,
      "mode": "1"
    }
  },
  {
    "obj": {
      "type": "0",
      "start_x": 0.0,
      "start_y": 0.0,
      "start_z": 0.0,
      "scale_x": 0.24,
      "scale_y": 0.036,
      "scale_z": 0.036,
      "rotation_x": 0.0,
      "rotation_y": 0.0,
      "rotation_z": 0.0,
      "mode": "1"
    }
  },
  {
    "obj": {
      "type": "0",
      "start_x": 0.15000000000000002,
      "start_y": 0.054,
      "start_z": 0.0,
      "scale_x": 0.19200000000000003,
      "scale_y": 0.0288,
      "scale_z": 0.0288,
      "rotation_x": 0.0,
      "rotation_y": 0.0,
      "rotation_z": 0.3,
      "mode": "1"
    }
  },
  {
    "obj": {
      "type": "0",
      "start_x": 0.15000000000000002,
      "start_y": -0.054,
      "start_z": 0.0,
      "scale_x": 0.19200000000000003,
      "scale_y": 0.0288,
      "scale_z": 0.0288,
      "rotation_x": 0.0,
      "rotation_y": 0.0,
      "rotation_z": -0.3,
      "mode": "1"
    }
  },
  {
    "obj": {
      "type": "0",
      "start_x": 0.15000000000000002,
      "start_y": 0.054,
      "start_z": 0.0,
      "scale_x": 0.19200000000000003,
      "scale_y": 0.0288,
      "scale_z": 0.0288,
      "rotation_x": 0.0,
      "rotation_y": 0.0,
      "rotation_z": 0.3,
      "mode": "1"
    }
  },
  {
    "obj": {
      "type": "0",
      "start_x": 0.15000000000000002,
      "start_y": -0.054,
      "start_z": 0.0,
      "scale_x": 0.19200000000000003,
      "scale_y": 0.0288,
      "scale_z": 0.0288,
      "rotation_x": 0.0,
      "rotation_y": 0.0,
      "rotation_z": -0.3,
      "mode": "1"
    }
  },
  {
    "obj": {
      "type": "0",
      "start_x": 0.65,
      "start_y": 0.10200000000000001,
      "start_z": 0.0,
      "scale_x": 0.03840000000000003,
      "scale_y": 0.028799999999999992,
      "scale_z": 0.00288,
      "rotation_x": 0.0,
      "rotation_y": 0.0,
      "rotation_z": 0.3,
      "mode": "1"
    }
  },
  {
    "obj": {
      "type": "0",
      "start_x": 0.65,
      "start_y": -0.005999999999999998,
      "start_z": 0.0,
      "scale_x": 0.03840000000000003,
      "scale_y": 0.0288,
      "scale_z": 0.00288,
      "rotation_x": 0.0,
      "rotation_y": 0.0,
      "rotation_z": -0.3,
      "mode": "1"
    }
  },
  {
    "obj": {
      "type": "0",
      "start_x": 0.0,
      "start_y": 0.0,
      "start_z": 0.0,
      "scale_x": 0.24,
      "scale_y": 0.036,
      "scale_z": 0.036,
      "rotation_x": 0.0,
      "rotation_y": 0.0,
      "rotation_z": 0.0,
      "mode": "1"
    }
  },
  {
    "obj": {
      "type": "0",
      "start_x": 0.15000000000000002,
      "start_y": 0.054,
      "start_z": 0.0,
      "scale_x": 0.19200000000000003,
      "scale_y": 0.0288,
      "scale_z": 0.0288,
      "rotation_x": 0.0,
      "rotation_y": 0.0,
      "rotation_z": 0.3,
      "mode": "1"
    }
  },
  {
    "obj": {
      "type": "0",
      "start_x": 0.15000000000000002,
      "start_y": -0.054,
      "start_z": 0.0,
      "scale_x": 0.19200000000000003,
      "scale_y": 0.0288,
      "scale_z": 0.0288,
      "rotation_x": 0.0,
      "rotation_y": 0.0,
      "rotation_z": -0.3,
      "mode": "1"
    }
  },
  {
    "obj": {
      "type": "0",
      "start_x": 0.15000000000000002,
      "start_y": 0.054,
      "start_z": 0.0,
      "scale_x": 0.19200000000000003,
      "scale_y": 0.0288,
      "scale_z": 0.0288,
      "rotation_x": 0.0,
      "rotation_y": 0.0,
      "rotation_z": 0.3,
      "mode": "1"
    }
  },
  {
    "obj": {
      "type": "0",
      "start_x": 0.15000000000000002,
      "start_y": -0.054,
      "start_z": 0.0,
      "scale_x": 0.19200000000000003,
      "scale_y": 0.0288,
      "scale_z": 0.0288,
      "rotation_x": 0.0,
      "rotation_y": 0.0,
      "rotation_z": -0.3,
      "mode": "1"
    }
  },
  {
    "obj": {
      "type": "0",
      "start_x": 0.65,
      "start_y": 0.10200000000000001,
      "start_z": 0.0,
      "scale_x": 0.03840000000000003,
      "scale_y": 0.028799999999999992,
      "scale_z": 0.00288,
      "rotation_x": 0.0,
      "rotation_y": 0.0,
      "rotation_z": 0.3,
      "mode": "1"
    }
  },
  {
    "obj": {
      "type": "0",
      "start_x": 0.65,
      "start_y": -0.005999999999999998,
      "start_z": 0.0,
      "scale_x": 0.03840000000000003,
      "scale_y": 0.0288,
      "scale_z": 0.00288,
      "rotation_x": 0.0,
      "rotation_y": 0.0,
      "rotation_z": -0.3,
      "mode": "1"
    }
  },
  {
    "obj": {
      "type": "0",
      "start_x": 0.15000000000000002,
      "start_y": 0.054,
      "start_z": 0.0,
      "scale_x": 0.19200000000000003,
      "scale_y": 0.0288,
      "scale_z": 0.0288,
      "rotation_x": 0.0,
      "rotation_y": 0.0,
      "rotation_z": 0.3,
      "mode": "1"
    }
  },
  {
    "obj": {
      "type": "0",
      "start_x": 0.15000000000000002,
      "start_y": -0.054,
      "start_z": 0.0,
      "scale_x": 0.19200000000000003,
      "scale_y": 0.0288,
      "scale_z": 0.0288,
      "rotation_x": 0.0,
      "rotation_y": 0.0,
      "rotation_z": -0.3,
      "mode": "1"
    }
  },
  {
    "obj": {
      "type": "0",
      "start_x": 0.65,
      "start_y": 0.10200000000000001,
      "start_z": 0.0,
      "scale_x": 0.03840000000000003,
      "scale_y": 0.028799999999999992,
      "scale_z": 0.00288,
      "rotation_x": 0.0,
      "rotation_y": 0.0,
      "rotation_z": 0.3,
      "mode": "1"
    }
  },
  {
    "obj": {
      "type": "0",
      "start_x": 0.65,
      "start_y": -0.005999999999999998,
      "start_z": 0.0,
      "scale_x": 0.03840000000000003,
      "scale_y": 0.0288,
      "scale_z": 0.00288,
      "rotation_x": 0.0,
      "rotation_y": 0.0,
      "rotation_z": -0.3,
      "mode": "1"
    }
  },
  {
    "obj": {
      "type": "0",
      "start_x": 0.65,
      "start_y": 0.10200000000000001,
      "start_z": 0.0,
      "scale_x": 0.03840000000000003,
      "scale_y": 0.028799999999999992,
      "scale_z": 0.00288,
      "rotation_x": 0.0,
      "rotation_y": 0.0,
      "rotation_z": 0.3,
      "mode": "1"
    }
  },
  {
    "obj": {
      "type": "0",
      "start_x": 0.65,
      "start_y": -0.005999999999999998,
      "start_z": 0.0,
      "scale_x": 0.03840000000000003,
      "scale_y": 0.0288,
      "scale_z": 0.00288,
      "rotation_x": 0.0,
      "rotation_y": 0.0,
      "rotation_z": -0.3,
      "mode": "1"
    }
  },
  {
    "obj": {
      "type": "0",
      "start_x": 1.15,
      "start_y": 0.15,
      "start_z": 0.0,
      "scale_x": 0.007679999999999953,
      "scale_y": 0.028799999999999992,
      "scale_z": 0.000288,
      "rotation_x": 0.0,
      "rotation_y": 0.0,
      "rotation_z": 0.3,
      "mode": "1"
    }
  },
  {
    "obj": {
      "type": "0",
      "start_x": 1.15,
      "start_y": 0.042,
      "start_z": 0.0,
      "scale_x": 0.007679999999999953,
      "scale_y": 0.0288,
      "scale_z": 0.000288,
      "rotation_x": 0.0,
      "rotation_y": 0.0,
      "rotation_z": -0.3,
      "mode": "1"
    }
  }
]