[
  {
    "obj": {
      "type": 1,
      "start_x": 3.6452994616207475,
      "start_y": 3.8252994616207476,
      "start_z": 3.6452994616207475,
      "scale_x": 0.2,
      "scale_y": 0.02,
      "scale_z": 0.2
    }
  },
  {
    "obj": {
      "type": 4,
      "start_x": 3.1852994616207475,
      "start_y": 3.8252994616207476,
      "start_z": 3.6452994616207475,
      "scale_x": 0.26,
      "scale_y": 0.02,
      "scale_z": 0.02
    }
  },
  {
    "obj": {
      "type": 1,
      "start_x": 2.7252994616207475,
      "start_y": 3.8252994616207476,
      "start_z": 3.6452994616207475,
      "scale_x": 0.2,
      "scale_y": 0.02,
      "scale_z": 0.2
    }
  },
  {
    "obj": {
      "type": 2,
      "start_x": 2.7252994616207475,
      "start_y": 3.2252994616207475,
      "start_z": 3.6452994616207475,
      "scale_x": 0.02,
      "scale_y": 0.58,
      "scale_z": 0.02
    }
  },
  {
    "obj": {
      "type": 6,
      "start_x": 2.7252994616207475,
      "start_y": 3.8252994616207476,
      "start_z": 3.245299461620747,
      "scale_x": 0.02,
      "scale_y": 0.02,
      "scale_z": 0.2
    }
  },
  {
    "obj": {
      "type": 3,
      "start_x": 3.2479491924311215,
      "start_y": 3.0679491924311213,
      "start_z": 3.2479491924311215,
      "scale_x": 0.02,
      "scale_y": 0.2,
      "scale_z": 0.02
    }
  },
  {
    "obj": {
      "type": 1,
      "start_x": 3.2479491924311215,
      "start_y": 2.847949192431121,
      "start_z": 3.2479491924311215,
      "scale_x": 0.2,
      "scale_y": 0.02,
      "scale_z": 0.2
    }
  },
  {
    "obj": {
      "type": 5,
      "start_x": 3.7279491924311214,
      "start_y": 2.847949192431121,
      "start_z": 3.2479491924311215,
      "scale_x": 0.28,
      "scale_y": 0.02,
      "scale_z": 0.02
    }
  },
  {
    "obj": {
      "type": 1,
      "start_x": 4.207949192431122,
      "start_y": 2.847949192431121,
      "start_z": 3.2479491924311215,
      "scale_x": 0.2,
      "scale_y": 0.02,
      "scale_z": 0.2
    }
  },
  {
    "obj": {
      "type": 6,
      "start_x": 4.207949192431122,
      "start_y": 2.847949192431121,
      "start_z": 2.7579491924311212,
      "scale_x": 0.02,
      "scale_y": 0.02,
      "scale_z": 0.29
    }
  }
]