[
  {
    "obj": {
      "type": 1,
      "start_x": 2.5197989232414955,
      "start_y": 2.6387989232414952,
      "start_z": 2.5405989232414954,
      "scale_x": 0.1708,
      "scale_y": 0.0518,
      "scale_z": 0.15,
      "mode": "1"
    }
  },
  {
    "obj": {
      "type": 7,
      "start_x": 2.5197989232414955,
      "start_y": 2.6387989232414952,
      "start_z": 2.909198923241495,
      "scale_x": 0.02,
      "scale_y": 0.02,
      "scale_z": 0.2186,
      "mode": "1"
    }
  },
  {
    "obj": {
      "type": 1,
      "start_x": 2.5197989232414955,
      "start_y": 2.6387989232414952,
      "start_z": 3.260998923241495,
      "scale_x": 0.1969,
      "scale_y": 0.072,
      "scale_z": 0.1332,
      "mode": "1"
    }
  },
  {
    "obj": {
      "type": 5,
      "start_x": 3.013998923241495,
      "start_y": 2.6387989232414952,
      "start_z": 3.260998923241495,
      "scale_x": 0.2973,
      "scale_y": 0.02,
      "scale_z": 0.02,
      "mode": "1"
    }
  },
  {
    "obj": {
      "type": 1,
      "start_x": 3.508498923241495,
      "start_y": 2.6387989232414952,
      "start_z": 3.260998923241495,
      "scale_x": 0.1972,
      "scale_y": 0.0842,
      "scale_z": 0.1532,
      "mode": "1"
    }
  },
  {
    "obj": {
      "type": 3,
      "start_x": 0.3611978464829906,
      "start_y": 0.2549978464829906,
      "start_z": 0.3611978464829906,
      "scale_x": 0.02,
      "scale_y": 0.1262,
      "scale_z": 0.02,
      "mode": "1"
    }
  },
  {
    "obj": {
      "type": 1,
      "start_x": 0.3611978464829906,
      "start_y": 0.07189784648299061,
      "start_z": 0.3611978464829906,
      "scale_x": 0.1503,
      "scale_y": 0.0569,
      "scale_z": 0.161,
      "mode": "1"
    }
  },
  {
    "obj": {
      "type": 7,
      "start_x": 0.3611978464829906,
      "start_y": 0.07189784648299061,
      "start_z": 0.8130978464829905,
      "scale_x": 0.02,
      "scale_y": 0.02,
      "scale_z": 0.2909,
      "mode": "1"
    }
  },
  {
    "obj": {
      "type": 1,
      "start_x": 0.3611978464829906,
      "start_y": 0.07189784648299061,
      "start_z": 1.2737978464829904,
      "scale_x": 0.1872,
      "scale_y": 0.0681,
      "scale_z": 0.1698,
      "mode": "1"
    }
  },
  {
    "obj": {
      "type": 4,
      "start_x": -0.1357021535170094,
      "start_y": 0.07189784648299061,
      "start_z": 1.2737978464829904,
      "scale_x": 0.3097,
      "scale_y": 0.02,
      "scale_z": 0.02,
      "mode": "1"
    }
  },
  {
    "obj": {
      "type": 1,
      "start_x": -0.6417021535170094,
      "start_y": 0.07189784648299061,
      "start_z": 1.2737978464829904,
      "scale_x": 0.1963,
      "scale_y": 0.0638,
      "scale_z": 0.1561,
      "mode": "1"
    }
  },
  {
    "obj": {
      "type": 1,
      "start_x": -0.6417021535170094,
      "start_y": 0.07189784648299061,
      "start_z": 1.2737978464829904,
      "scale_x": 0.1963,
      "scale_y": 0.0638,
      "scale_z": 0.1561,
      "mode": "1"
    }
  },
  {
    "obj": {
      "type": 8,
      "start_x": -0.6417021535170094,
      "start_y": 0.5356978464829907,
      "start_z": 1.2737978464829904,
      "scale_x": 0.02,
      "scale_y": 0.4,
      "scale_z": 0.02,
      "mode": "1"
    }
  },
  {
    "obj": {
      "type": 1,
      "start_x": -0.6417021535170094,
      "start_y": 1.0356978464829907,
      "start_z": 1.2737978464829904,
      "scale_x": 0.1928,
      "scale_y": 0.1,
      "scale_z": 0.1109,
      "mode": "1"
    }
  },
  {
    "obj": {
      "type": 8,
      "start_x": -0.6417021535170094,
      "start_y": 1.463998384862243,
      "start_z": 1.2737978464829904,
      "scale_x": 0.02,
      "scale_y": 0.3283005383792523,
      "scale_z": 0.02,
      "mode": "1"
    }
  },
  {
    "obj": {
      "type": 1,
      "start_x": -0.6417021535170094,
      "start_y": 1.8780989232414955,
      "start_z": 1.2737978464829904,
      "scale_x": 0.1998,
      "scale_y": 0.0858,
      "scale_z": 0.1112,
      "mode": "1"
    }
  },
  {
    "obj": {
      "type": 8,
      "start_x": -0.6417021535170094,
      "start_y": 2.256298923241496,
      "start_z": 1.2737978464829904,
      "scale_x": 0.02,
      "scale_y": 0.2924,
      "scale_z": 0.02,
      "mode": "1"
    }
  },
  {
    "obj": {
      "type": 1,
      "start_x": -0.6417021535170094,
      "start_y": 2.6387989232414957,
      "start_z": 1.2737978464829904,
      "scale_x": 0.1157,
      "scale_y": 0.0901,
      "scale_z": 0.1089,
      "mode": "1"
    }
  },
  {
    "obj": {
      "type": 5,
      "start_x": -0.17600215351700943,
      "start_y": 2.6387989232414957,
      "start_z": 1.2737978464829904,
      "scale_x": 0.35,
      "scale_y": 0.02,
      "scale_z": 0.02,
      "mode": "1"
    }
  },
  {
    "obj": {
      "type": 1,
      "start_x": 0.37399784648299056,
      "start_y": 2.6387989232414957,
      "start_z": 1.2737978464829904,
      "scale_x": 0.2,
      "scale_y": 0.0572,
      "scale_z": 0.1273,
      "mode": "1"
    }
  },
  {
    "obj": {
      "type": 5,
      "start_x": 0.9239978464829905,
      "start_y": 2.6387989232414957,
      "start_z": 1.2737978464829904,
      "scale_x": 0.35,
      "scale_y": 0.02,
      "scale_z": 0.02,
      "mode": "1"
    }
  },
  {
    "obj": {
      "type": 1,
      "start_x": 1.4739978464829904,
      "start_y": 2.6387989232414957,
      "start_z": 1.2737978464829904,
      "scale_x": 0.2,
      "scale_y": 0.0532,
      "scale_z": 0.1826,
      "mode": "1"
    }
  },
  {
    "obj": {
      "type": 5,
      "start_x": 2.013648384862243,
      "start_y": 2.6387989232414957,
      "start_z": 1.2737978464829904,
      "scale_x": 0.3396505383792526,
      "scale_y": 0.02,
      "scale_z": 0.02,
      "mode": "1"
    }
  },
  {
    "obj": {
      "type": 1,
      "start_x": 2.5197989232414955,
      "start_y": 2.6387989232414957,
      "start_z": 1.2737978464829904,
      "scale_x": 0.1665,
      "scale_y": 0.0742,
      "scale_z": 0.175,
      "mode": "1"
    }
  },
  {
    "obj": {
      "type": 7,
      "start_x": 2.5197989232414955,
      "start_y": 2.6387989232414957,
      "start_z": 1.5987978464829904,
      "scale_x": 0.02,
      "scale_y": 0.02,
      "scale_z": 0.15,
      "mode": "1"
    }
  },
  {
    "obj": {
      "type": 1,
      "start_x": 2.5197989232414955,
      "start_y": 2.6387989232414957,
      "start_z": 1.8487978464829904,
      "scale_x": 0.1617,
      "scale_y": 0.0724,
      "scale_z": 0.1,
      "mode": "1"
    }
  },
  {
    "obj": {
      "type": 7,
      "start_x": 2.5197989232414955,
      "start_y": 2.6387989232414957,
      "start_z": 2.169698384862243,
      "scale_x": 0.02,
      "scale_y": 0.02,
      "scale_z": 0.22090053837925244,
      "mode": "1"
    }
  }
]